Workbook

Sheet הגדרות
A1: הגדרות ופרמטרים – AI & Business Tools Expenses
A3: שער חליפין
A4: שער USD → ILS (מתעדכן אוטומטית) | B4: 2.962 | C4: ← מקור: Bank of Israel Public API | עודכן: 2026-05-04
A6: הערה: | B6: כל הסכומים בשקלים מחושבים על פי השיעור שמוגדר בתא B4. ניתן לשנות שיעור זה לפי השיעור היסטורי הרצוי. שיעורי ההמרה בפועל ששולמו עשויים להיות שונים מעט בשל עמלות המרה.
A10: חיובים קבועים: | B10: OpenAI / ChatGPT Plus – $20 בכל 16 לחודש. החיוב מתווסף אוטומטית לכל חודש בדוחות, בגליונות ובדשבורד, וכאשר תגיע חשבונית OpenAI במייל היא אמורה להיות מזוהה תחת אותו כלי.

Sheet כל ההוצאות
A1: כל ההוצאות – כלי AI | יולי 2025 – דצמבר 2026
A2: תאריך | B2: כלי | C2: תיאור | D2: סכום ($) | E2: סכום (₪) | F2: חודש
A3: 2025-07-04 | B3: Recraft | C3: Basic – first month promo | D3: 1.127616 | E3: 3.34 | F3: יולי 2025
A4: 2025-07-09 | B4: Ideogram AI | C4: Ideogram Basic – annual | D4: 81.390952 | E4: 241.08 | F4: יולי 2025
A5: 2025-07-10 | B5: Make | C5: Core plan 10k ops/month | D5: 11.829845 | E5: 35.04 | F5: יולי 2025
A6: 2025-07-11 | B6: Anthropic | C6: Claude Pro | D6: 22.383525 | E6: 66.3 | F6: יולי 2025
A7: 2025-07-16 | B7: OpenAI | C7: ChatGPT Plus | D7: 20 | E7: 67.31 | F7: יולי 2025
A8: 2025-07-20 | B8: Runway ML | C8: Standard (10% affiliate off) | D8: 15.303849 | E8: 45.33 | F8: יולי 2025
A9: 2025-07-30 | B9: Ideogram AI | C9: Upgrade -> Plus Annual | D9: 128.58204 | E9: 380.86 | F9: יולי 2025
A10: 2025-07-30 | B10: Replicate | C10: Early card charge | D10: 11.363943 | E10: 33.66 | F10: יולי 2025
A11: 2025-08-01 | B11: Google Workspace | C11: Business Plus – Jul 2025 (₪56.93) | D11: 19.220122 | E11: 56.93 | F11: אוגוסט 2025
A12: 2025-08-02 | B12: Runway ML | C12: Credits 1,500 | D12: 17.282242 | E12: 51.19 | F12: אוגוסט 2025
A13: 2025-08-04 | B13: Recraft | C13: Basic monthly | D13: 13.81499 | E13: 40.92 | F13: אוגוסט 2025
A14: 2025-08-05 | B14: Replicate | C14: Usage - July | D14: 1.039838 | E14: 3.08 | F14: אוגוסט 2025
... A133: 2026-12-16 | B133: OpenAI | C133: ChatGPT Plus | D133: 20 | E133: 73 | F133: דצמבר 2026
A134: סה"כ" | D134: =SUM(D3:D133) | E134: =SUM(E3:E133)

Sheet יולי 2025
A1: יולי 2025 | July 2025
A2: ← חזרה לסיכום חודשי
A3: תאריך | B3: כלי | C3: תיאור | D3: סכום ($) | E3: סכום (₪)
A4: 2025-07-04 | B4: Recraft | C4: Basic – first month promo | D4: 1.127616 | E4: 3.34
A5: 2025-07-09 | B5: Ideogram AI | C5: Ideogram Basic – annual | D5: 81.390952 | E5: 241.08
A6: 2025-07-10 | B6: Make | C6: Core plan 10k ops/month | D6: 11.829845 | E6: 35.04
A7: 2025-07-11 | B7: Anthropic | C7: Claude Pro | D7: 22.383525 | E7: 66.3
A8: 2025-07-16 | B8: OpenAI | C8: ChatGPT Plus | D8: 20 | E8: 67.31
A9: 2025-07-20 | B9: Runway ML | C9: Standard (10% affiliate off) | D9: 15.303849 | E9: 45.33
A10: 2025-07-30 | B10: Ideogram AI | C10: Upgrade -> Plus Annual | D10: 128.58204 | E10: 380.86
A11: 2025-07-30 | B11: Replicate | C11: Early card charge | D11: 11.363943 | E11: 33.66
A12: סה"כ חודש" | D12: =SUM(D4:D11) | E12: =SUM(E4:E11)

Sheet אוגוסט 2025
A1: אוגוסט 2025 | August 2025
A2: ← חזרה לסיכום חודשי
A3: תאריך | B3: כלי | C3: תיאור | D3: סכום ($) | E3: סכום (₪)
A4: 2025-08-01 | B4: Google Workspace | C4: Business Plus – Jul 2025 (₪56.93) | D4: 19.220122 | E4: 56.93
A5: 2025-08-02 | B5: Runway ML | C5: Credits 1,500 | D5: 17.282242 | E5: 51.19
A6: 2025-08-04 | B6: Recraft | C6: Basic monthly | D6: 13.81499 | E6: 40.92
A7: 2025-08-05 | B7: Replicate | C7: Usage - July | D7: 1.039838 | E7: 3.08
A8: 2025-08-09 | B8: Manus AI | C8: Basic monthly | D8: 22.025658 | E8: 65.24
A9: 2025-08-10 | B9: Make | C9: Core plan 10k ops/month | D9: 12.27549 | E9: 36.36
A10: 2025-08-11 | B10: Anthropic | C10: Claude Pro | D10: 23.102633 | E10: 68.43
A11: 2025-08-16 | B11: OpenAI | C11: ChatGPT Plus | D11: 20 | E11: 67.54
A12: 2025-08-30 | B12: Eleven Labs | C12: Starter monthly | D12: 5.641458 | E12: 16.71
A13: 2025-08-30 | B13: Runway ML | C13: Standard (25% off) | D13: 12.694126 | E13: 37.6
A14: סה"כ חודש" | D14: =SUM(D4:D13) | E14: =SUM(E4:E13)

Sheet ספטמבר 2025
A1: ספטמבר 2025 | September 2025
A2: ← חזרה לסיכום חודשי
A3: תאריך | B3: כלי | C3: תיאור | D3: סכום ($) | E3: סכום (₪)
A4: 2025-09-01 | B4: Google Workspace | C4: Business Plus – Aug 2025 (₪56.93) | D4: 19.220122 | E4: 56.93
A5: 2025-09-05 | B5: Replicate | C5: Usage - August | D5: 3.153275 | E5: 9.34
A6: 2025-09-10 | B6: Make | C6: Core plan 10k ops/month | D6: 11.95476 | E6: 35.41
A7: 2025-09-16 | B7: OpenAI | C7: ChatGPT Plus | D7: 20 | E7: 67.01
A8: 2025-09-24 | B8: Anthropic | C8: Claude Pro | D8: 22.572586 | E8: 66.86
A9: 2025-09-30 | B9: Eleven Labs | C9: Starter monthly | D9: 5.573937 | E9: 16.51
A10: סה"כ חודש" | D10: =SUM(D4:D9) | E10: =SUM(E4:E9)

Sheet אוקטובר 2025
A1: אוקטובר 2025 | October 2025
A2: ← חזרה לסיכום חודשי
A3: תאריך | B3: כלי | C3: תיאור | D3: סכום ($) | E3: סכום (₪)
A4: 2025-10-02 | B4: Google Workspace | C4: Business Plus – Sep 2025 (₪56.93) | D4: 19.220122 | E4: 56.93
A5: 2025-10-16 | B5: OpenAI | C5: ChatGPT Plus | D5: 20 | E5: 65.72
A6: 2025-10-24 | B6: Anthropic | C6: Claude Pro | D6: 22.21472 | E6: 65.8
A7: 2025-10-30 | B7: Eleven Labs | C7: Starter monthly | D7: 5.49291 | E7: 16.27
A8: סה"כ חודש" | D8: =SUM(D4:D7) | E8: =SUM(E4:E7)

Sheet נובמבר 2025
A1: נובמבר 2025 | November 2025
A2: ← חזרה לסיכום חודשי
A3: תאריך | B3: כלי | C3: תיאור | D3: סכום ($) | E3: סכום (₪)
A4: 2025-11-09 | B4: Recraft | C4: Pro 1k credits | D4: 13.207292 | E4: 39.12
A5: 2025-11-11 | B5: Astria | C5: Credits x10 + 18% VAT | D5: 12.86293 | E5: 38.1
A6: 2025-11-11 | B6: Runway ML | C6: Standard monthly | D6: 16.353815 | E6: 48.44
A7: 2025-11-13 | B7: Hedra | C7: Extra Small Credit Pack | D7: 10.786631 | E7: 31.95
A8: 2025-11-16 | B8: OpenAI | C8: ChatGPT Plus | D8: 20 | E8: 64.68
A9: 2025-11-24 | B9: Anthropic | C9: Claude Pro | D9: 22.120189 | E9: 65.52
A10: 2025-11-30 | B10: Eleven Labs | C10: Starter monthly | D10: 5.506415 | E10: 16.31
A11: סה"כ חודש" | D11: =SUM(D4:D10) | E11: =SUM(E4:E10)

Sheet דצמבר 2025
A1: דצמבר 2025 | December 2025
A2: ← חזרה לסיכום חודשי
A3: תאריך | B3: כלי | C3: תיאור | D3: סכום ($) | E3: סכום (₪)
A4: 2025-12-01 | B4: Google Workspace | C4: Business Plus – Nov 2025 (₪75.90) | D4: 25.624578 | E4: 75.9
A5: 2025-12-03 | B5: Manychat | C5: Pro monthly | D5: 16.468602 | E5: 48.78
A6: 2025-12-03 | B6: Meta (Ads) | C6: Facebook Ads | D6: 10.671843 | E6: 31.61
A7: 2025-12-08 | B7: Meta (Ads) | C7: Facebook Ads | D7: 32.734639 | E7: 96.96
A8: 2025-12-16 | B8: Meta (Ads) | C8: Facebook Ads | D8: 35.796759 | E8: 106.03
A9: 2025-12-16 | B9: OpenAI | C9: ChatGPT Plus | D9: 20 | E9: 64.26
A10: 2025-12-29 | B10: Meta (Ads) | C10: Facebook Ads | D10: 38.760972 | E10: 114.81
A11: 2025-12-30 | B11: Eleven Labs | C11: Starter monthly | D11: 5.378123 | E11: 15.93
A12: סה"כ חודש" | D12: =SUM(D4:D11) | E12: =SUM(E4:E11)

Sheet ינואר 2026
A1: ינואר 2026 | January 2026
A2: ← חזרה לסיכום חודשי
A3: תאריך | B3: כלי | C3: תיאור | D3: סכום ($) | E3: סכום (₪)
A4: 2026-01-01 | B4: Google Workspace | C4: Business Plus – Dec 2025 (₪75.90) | D4: 25.624578 | E4: 75.9
A5: 2026-01-03 | B5: Genspark | C5: Plus Annual (happynewyear26 promo) | D5: 150.48278 | E5: 445.73
A6: 2026-01-03 | B6: Manychat | C6: Pro monthly | D6: 16.130993 | E6: 47.78
A7: 2026-01-03 | B7: Meta (Ads) | C7: Facebook Ads | D7: 20.898042 | E7: 61.9
A8: 2026-01-05 | B8: Genspark | C8: Credits Pack | D8: 21.441594 | E8: 63.51
A9: 2026-01-08 | B9: Genspark | C9: Credits Pack | D9: 21.380824 | E9: 63.33
A10: 2026-01-10 | B10: CapCut | C10: Pro – Jan 2026 (₪49.90) | D10: 16.846725 | E10: 49.9
A11: 2026-01-16 | B11: OpenAI | C11: ChatGPT Plus | D11: 20 | E11: 62.81
A12: 2026-01-19 | B12: Meta (Ads) | C12: Facebook Ads | D12: 41.458474 | E12: 122.8
A13: 2026-01-25 | B13: Lovable | C13: Pro 1 monthly | D13: 26.404456 | E13: 78.21
A14: 2026-01-27 | B14: Meta (Ads) | C14: Facebook Ads | D14: 45.239703 | E14: 134
A15: 2026-01-30 | B15: Eleven Labs | C15: Starter monthly | D15: 5.209318 | E15: 15.43
A16: 2026-01-30 | B16: Timeless | C16: Pro monthly (50% off) | D16: 15.104659 | E16: 44.74
A17: סה"כ חודש" | D17: =SUM(D4:D16) | E17: =SUM(E4:E16)

Sheet פברואר 2026
A1: פברואר 2026 | February 2026
A2: ← חזרה לסיכום חודשי
A3: תאריך | B3: כלי | C3: תיאור | D3: סכום ($) | E3: סכום (₪)
A4: 2026-02-01 | B4: Lovable | C4: Upgrade Pro1 -> Pro2 (prorated) | D4: 26.18501 | E4: 77.56
A5: 2026-02-02 | B5: Google Workspace | C5: Business Plus – Jan 2026 (₪75.90) | D5: 25.624578 | E5: 75.9
A6: 2026-02-03 | B6: Meta (Ads) | C6: Facebook Ads | D6: 32.873059 | E6: 97.37
A7: 2026-02-10 | B7: CapCut | C7: Pro – Feb 2026 (₪49.90) | D7: 16.846725 | E7: 49.9
A8: 2026-02-12 | B8: Meta (Ads) | C8: Facebook Ads | D8: 48.825118 | E8: 144.62
A9: 2026-02-15 | B9: Anthropic | C9: Claude Pro | D9: 20.840648 | E9: 61.73
A10: 2026-02-16 | B10: Anthropic | C10: Credit purchase | D10: 5.212694 | E10: 15.44
A11: 2026-02-16 | B11: OpenAI | C11: ChatGPT Plus | D11: 20 | E11: 61.77
A12: 2026-02-24 | B12: Higgsfield | C12: On-Demand credits 500 | D12: 21.120864 | E12: 62.56
A13: 2026-02-25 | B13: Lovable | C13: Pro2 monthly | D13: 52.316003 | E13: 154.96
A14: 2026-02-25 | B14: Meta (Ads) | C14: Facebook Ads | D14: 53.362593 | E14: 158.06
A15: 2026-02-28 | B15: Eleven Labs | C15: Starter monthly | D15: 5.29372 | E15: 15.68
A16: 2026-02-28 | B16: Lovable | C16: Cloud & AI Balance Top-up | D16: 10.584065 | E16: 31.35
A17: סה"כ חודש" | D17: =SUM(D4:D16) | E17: =SUM(E4:E16)

Sheet מרץ 2026
A1: מרץ 2026 | March 2026
A2: ← חזרה לסיכום חודשי
A3: תאריך | B3: כלי | C3: תיאור | D3: סכום ($) | E3: סכום (₪)
A4: 2026-03-01 | B4: Google Workspace | C4: Google Workspace (₪75.9) | D4: 25.624578 | E4: 75.9
A5: 2026-03-01 | B5: Lovable | C5: Cloud & AI Balance Top-up | D5: 10.560432 | E5: 31.28
A6: 2026-03-01 | B6: Timeless | C6: Pro monthly (50% off) | D6: 15.313977 | E6: 45.36
A7: 2026-03-02 | B7: Google Workspace | C7: Business Plus – Feb 2026 (₪75.90) | D7: 25.624578 | E7: 75.9
A8: 2026-03-02 | B8: Lovable | C8: Cloud & AI Balance Top-up | D8: 10.533423 | E8: 31.2
A9: 2026-03-03 | B9: Meta (Ads) | C9: Facebook Ads | D9: 41.671168 | E9: 123.43
A10: 2026-03-10 | B10: CapCut | C10: Pro – Mar 2026 (₪49.90) | D10: 16.846725 | E10: 49.9
A11: 2026-03-12 | B11: Meta (Ads) | C11: Facebook Ads | D11: 53.906144 | E11: 159.67
A12: 2026-03-15 | B12: Anthropic | C12: Claude Pro | D12: 21.225523 | E12: 62.87
A13: 2026-03-16 | B13: OpenAI | C13: ChatGPT Plus | D13: 20 | E13: 62.87
A14: 2026-03-18 | B14: CapCut | C14: Pro – Mar 2026 (₪49.90) | D14: 16.846725 | E14: 49.9
A15: 2026-03-19 | B15: Anthropic | C15: Credit purchase | D15: 10.503038 | E15: 31.11
... A19: 2026-03-26 | B19: Dzine | C19: Video Top-Up | D19: 21.056718 | E19: 62.37
A20: סה"כ חודש" | D20: =SUM(D4:D19) | E20: =SUM(E4:E19)

Sheet אפריל 2026
A1: אפריל 2026 | April 2026
A2: ← חזרה לסיכום חודשי
A3: תאריך | B3: כלי | C3: תיאור | D3: סכום ($) | E3: סכום (₪)
A4: 2026-04-01 | B4: Anthropic | C4: Prepaid extra usage, Individual plan | D4: 10.61445 | E4: 31.44
A5: 2026-04-01 | B5: Google Workspace | C5: Business Plus – Mar 2026 (₪75.90) | D5: 25.624578 | E5: 75.9
A6: 2026-04-01 | B6: Meta (Ads) | C6: Facebook Ads | D6: 56.154625 | E6: 166.33
A7: 2026-04-02 | B7: Dzine | C7: Video Top-Up | D7: 19.071573 | E7: 56.49
A8: 2026-04-03 | B8: Meta (Ads) | C8: Facebook Ads | D8: 2.380149 | E8: 7.05
A9: 2026-04-05 | B9: IONOS | C9: Instant Domain | D9: 21.212019 | E9: 62.83
A10: 2026-04-10 | B10: CapCut | C10: capcut_pro_discount1 | D10: 16.846725 | E10: 49.9
A11: 2026-04-15 | B11: Anthropic | C11: Claude Pro | D11: 20 | E11: 60.19
A12: 2026-04-16 | B12: Anthropic | C12: Prepaid extra usage, Individual plan | D12: 10 | E12: 29.98
A13: 2026-04-16 | B13: OpenAI | C13: ChatGPT Plus | D13: 20 | E13: 59.96
A14: 2026-04-18 | B14: CapCut | C14: Pro – Apr 2026 (₪49.90) | D14: 16.846725 | E14: 49.9
A15: 2026-04-18 | B15: OpenAI | C15: ChatGPT Pro Subscription | D15: 81.141121 | E15: 240.34
... A31: 2026-04-28 | B31: Anthropic | C31: Auto recharge extra usage, Individual plan | D31: 10.56 | E31: 31.42
A32: סה"כ חודש" | D32: =SUM(D4:D31) | E32: =SUM(E4:E31)

Sheet מאי 2026
A1: מאי 2026 | May 2026
A2: ← חזרה לסיכום חודשי
A3: תאריך | B3: כלי | C3: תיאור | D3: סכום ($) | E3: סכום (₪)
A4: 2026-05-01 | B4: Anthropic | C4: Auto recharge extra usage, Individual plan | D4: 10.367995 | E4: 30.71
A5: 2026-05-01 | B5: Anthropic | C5: Auto recharge extra usage, Individual plan | D5: 10.806887 | E5: 32.01
A6: 2026-05-01 | B6: Anthropic | C6: Auto recharge extra usage, Individual plan | D6: 10.786631 | E6: 31.95
A7: 2026-05-01 | B7: Google Cloud | C7: Google Cloud Platform & APIs (₪8.23) | D7: 2.778528 | E7: 8.23
A8: 2026-05-01 | B8: Google Workspace | C8: Google Workspace (₪75.90) | D8: 25.624578 | E8: 75.9
A9: 2026-05-02 | B9: Anthropic | C9: Prepaid extra usage, Individual plan | D9: 4.976367 | E9: 14.74
A10: 2026-05-03 | B10: Anthropic | C10: Auto recharge extra usage, Individual plan | D10: 15.256583 | E10: 45.19
A11: 2026-05-03 | B11: Meta (Ads) | C11: Facebook Ads | D11: 27.150574 | E11: 80.42
A12: 2026-05-04 | B12: Anthropic | C12: Auto recharge extra usage, Individual plan | D12: 15.290344 | E12: 45.29
A13: 2026-05-04 | B13: Eleven Labs | C13: Creator monthly | D13: 21.863606 | E13: 64.76
A14: 2026-05-16 | B14: OpenAI | C14: ChatGPT Plus | D14: 20 | E14: 73
A15: סה"כ חודש" | D15: =SUM(D4:D14) | E15: =SUM(E4:E14)

Sheet יוני 2026
A1: יוני 2026 | June 2026
A2: ← חזרה לסיכום חודשי
A3: תאריך | B3: כלי | C3: תיאור | D3: סכום ($) | E3: סכום (₪)
A4: 2026-06-16 | B4: OpenAI | C4: ChatGPT Plus | D4: 20 | E4: 73
A5: סה"כ חודש" | D5: =SUM(D4:D4) | E5: =SUM(E4:E4)

Sheet יולי 2026
A1: יולי 2026 | July 2026
A2: ← חזרה לסיכום חודשי
A3: תאריך | B3: כלי | C3: תיאור | D3: סכום ($) | E3: סכום (₪)
A4: 2026-07-16 | B4: OpenAI | C4: ChatGPT Plus | D4: 20 | E4: 73
A5: סה"כ חודש" | D5: =SUM(D4:D4) | E5: =SUM(E4:E4)

Sheet אוגוסט 2026
A1: אוגוסט 2026 | August 2026
A2: ← חזרה לסיכום חודשי
A3: תאריך | B3: כלי | C3: תיאור | D3: סכום ($) | E3: סכום (₪)
A4: 2026-08-16 | B4: OpenAI | C4: ChatGPT Plus | D4: 20 | E4: 73
A5: סה"כ חודש" | D5: =SUM(D4:D4) | E5: =SUM(E4:E4)

Sheet ספטמבר 2026
A1: ספטמבר 2026 | September 2026
A2: ← חזרה לסיכום חודשי
A3: תאריך | B3: כלי | C3: תיאור | D3: סכום ($) | E3: סכום (₪)
A4: 2026-09-16 | B4: OpenAI | C4: ChatGPT Plus | D4: 20 | E4: 73
A5: סה"כ חודש" | D5: =SUM(D4:D4) | E5: =SUM(E4:E4)

Sheet אוקטובר 2026
A1: אוקטובר 2026 | October 2026
A2: ← חזרה לסיכום חודשי
A3: תאריך | B3: כלי | C3: תיאור | D3: סכום ($) | E3: סכום (₪)
A4: 2026-10-16 | B4: OpenAI | C4: ChatGPT Plus | D4: 20 | E4: 73
A5: סה"כ חודש" | D5: =SUM(D4:D4) | E5: =SUM(E4:E4)

Sheet נובמבר 2026
A1: נובמבר 2026 | November 2026
A2: ← חזרה לסיכום חודשי
A3: תאריך | B3: כלי | C3: תיאור | D3: סכום ($) | E3: סכום (₪)
A4: 2026-11-16 | B4: OpenAI | C4: ChatGPT Plus | D4: 20 | E4: 73
A5: סה"כ חודש" | D5: =SUM(D4:D4) | E5: =SUM(E4:E4)

Sheet דצמבר 2026
A1: דצמבר 2026 | December 2026
A2: ← חזרה לסיכום חודשי
A3: תאריך | B3: כלי | C3: תיאור | D3: סכום ($) | E3: סכום (₪)
A4: 2026-12-16 | B4: OpenAI | C4: ChatGPT Plus | D4: 20 | E4: 73
A5: סה"כ חודש" | D5: =SUM(D4:D4) | E5: =SUM(E4:E4)

Sheet סיכום חודשי
A1: סיכום חודשי לפי כלי | יולי 2025 – דצמבר 2026
A2: לחץ על שם חודש כדי לצפייה בגליון המפורט ↓ | OpenAI / ChatGPT Plus מתווסף אוטומטית ב-16 לכל חודש
A3: כלי | B3: יולי 2025 (July 2025) | D3: אוגוסט 2025 (August 2025) | F3: ספטמבר 2025 (September 2025) | H3: אוקטובר 2025 (October 2025) | J3: נובמבר 2025 (November 2025) | L3: דצמבר 2025 (December 2025) | N3: ינואר 2026 (January 2026) | P3: פברואר 2026 (February 2026) | R3: מרץ 2026 (March 2026) | T3: אפריל 2026 (April 2026) | V3: מאי 2026 (May 2026) | X3: יוני 2026 (June 2026) | Z3: יולי 2026 (July 2026) | AB3: אוגוסט 2026 (August 2026) | AD3: ספטמבר 2026 (September 2026) | AF3: אוקטובר 2026 (October 2026) | AH3: נובמבר 2026 (November 2026) | AJ3: דצמבר 2026 (December 2026) | AL3: סה"כ ($) | AM3: סה"כ (₪)
B4: $ | C4: ₪ | D4: $ | E4: ₪ | F4: $ | G4: ₪ | H4: $ | I4: ₪ | J4: $ | K4: ₪ | L4: $ | M4: ₪ | N4: $ | O4: ₪ | P4: $ | Q4: ₪ | R4: $ | S4: ₪ | T4: $ | U4: ₪ | V4: $ | W4: ₪ | X4: $ | Y4: ₪ | Z4: $ | AA4: ₪ | AB4: $ | AC4: ₪ | AD4: $ | AE4: ₪ | AF4: $ | AG4: ₪ | AH4: $ | AI4: ₪ | AJ4: $ | AK4: ₪ | AL4: $ | AM4: ₪
A5: Anthropic | B5: =SUMIFS('כל ההוצאות'!$D:$D,'כל ההוצאות'!$B:$B,"Anthropic",'כל ההוצאות'!$F:$F,"יולי 2025") | C5: =SUMIFS('כל ההוצאות'!$E:$E,'כל ההוצאות'!$B:$B,"Anthropic",'כל ההוצאות'!$F:$F,"יולי 2025") | D5: =SUMIFS('כל ההוצאות'!$D:$D,'כל ההוצאות'!$B:$B,"Anthropic",'כל ההוצאות'!$F:$F,"אוגוסט 2025") | E5: =SUMIFS('כל ההוצאות'!$E:$E,'כל ההוצאות'!$B:$B,"Anthropic",'כל ההוצאות'!$F:$F,"אוגוסט 2025") | F5: =SUMIFS('כל ההוצאות'!$D:$D,'כל ההוצאות'!$B:$B,"Anthropic",'כל ההוצאות'!$F:$F,"ספטמבר 2025") | G5: =SUMIFS('כל ההוצאות'!$E:$E,'כל ההוצאות'!$B:$B,"Anthropic",'כל ההוצאות'!$F:$F,"ספטמבר 2025") | H5: =SUMIFS('כל ההוצאות'!$D:$D,'כל ההוצאות'!$B:$B,"Anthropic",'כל ההוצאות'!$F:$F,"אוקטובר 2025") | I5: =SUMIFS('כל ההוצאות'!$E:$E,'כל ההוצאות'!$B:$B,"Anthropic",'כל ההוצאות'!$F:$F,"אוקטובר 2025") | J5: =SUMIFS('כל ההוצאות'!$D:$D,'כל ההוצאות'!$B:$B,"Anthropic",'כל ההוצאות'!$F:$F,"נובמבר 2025") | K5: =SUMIFS('כל ההוצאות'!$E:$E,'כל ההוצאות'!$B:$B,"Anthropic",'כל ההוצאות'!$F:$F,"נובמבר 2025") | L5: =SUMIFS('כל ההוצאות'!$D:$D,'כל ההוצאות'!$B:$B,"Anthropic",'כל ההוצאות'!$F:$F,"דצמבר 2025") | M5: =SUMIFS('כל ההוצאות'!$E:$E,'כל ההוצאות'!$B:$B,"Anthropic",'כל ההוצאות'!$F:$F,"דצמבר 2025") | N5: =SUMIFS('כל ההוצאות'!$D:$D,'כל ההוצאות'!$B:$B,"Anthropic",'כל ההוצאות'!$F:$F,"ינואר 2026") | O5: =SUMIFS('כל ההוצאות'!$E:$E,'כל ההוצאות'!$B:$B,"Anthropic",'כל ההוצאות'!$F:$F,"ינואר 2026") | P5: =SUMIFS('כל ההוצאות'!$D:$D,'כל ההוצאות'!$B:$B,"Anthropic",'כל ההוצאות'!$F:$F,"פברואר 2026") | Q5: =SUMIFS('כל ההוצאות'!$E:$E,'כל ההוצאות'!$B:$B,"Anthropic",'כל ההוצאות'!$F:$F,"פברואר 2026") | R5: =SUMIFS('כל ההוצאות'!$D:$D,'כל ההוצאות'!$B:$B,"Anthropic",'כל ההוצאות'!$F:$F,"מרץ 2026") | S5: =SUMIFS('כל ההוצאות'!$E:$E,'כל ההוצאות'!$B:$B,"Anthropic",'כל ההוצאות'!$F:$F,"מרץ 2026") | T5: =SUMIFS('כל ההוצאות'!$D:$D,'כל ההוצאות'!$B:$B,"Anthropic",'כל ההוצאות'!$F:$F,"אפריל 2026") | U5: =SUMIFS('כל ההוצאות'!$E:$E,'כל ההוצאות'!$B:$B,"Anthropic",'כל ההוצאות'!$F:$F,"אפריל 2026") | V5: =SUMIFS('כל ההוצאות'!$D:$D,'כל ההוצאות'!$B:$B,"Anthropic",'כל ההוצאות'!$F:$F,"מאי 2026") | W5: =SUMIFS('כל ההוצאות'!$E:$E,'כל ההוצאות'!$B:$B,"Anthropic",'כל ההוצאות'!$F:$F,"מאי 2026") | X5: =SUMIFS('כל ההוצאות'!$D:$D,'כל ההוצאות'!$B:$B,"Anthropic",'כל ההוצאות'!$F:$F,"יוני 2026") | Y5: =SUMIFS('כל ההוצאות'!$E:$E,'כל ההוצאות'!$B:$B,"Anthropic",'כל ההוצאות'!$F:$F,"יוני 2026") | Z5: =SUMIFS('כל ההוצאות'!$D:$D,'כל ההוצאות'!$B:$B,"Anthropic",'כל ההוצאות'!$F:$F,"יולי 2026") | AA5: =SUMIFS('כל ההוצאות'!$E:$E,'כל ההוצאות'!$B:$B,"Anthropic",'כל ההוצאות'!$F:$F,"יולי 2026") | AB5: =SUMIFS('כל ההוצאות'!$D:$D,'כל ההוצאות'!$B:$B,"Anthropic",'כל ההוצאות'!$F:$F,"אוגוסט 2026") | AC5: =SUMIFS('כל ההוצאות'!$E:$E,'כל ההוצאות'!$B:$B,"Anthropic",'כל ההוצאות'!$F:$F,"אוגוסט 2026") | AD5: =SUMIFS('כל ההוצאות'!$D:$D,'כל ההוצאות'!$B:$B,"Anthropic",'כל ההוצאות'!$F:$F,"ספטמבר 2026") | AE5: =SUMIFS('כל ההוצאות'!$E:$E,'כל ההוצאות'!$B:$B,"Anthropic",'כל ההוצאות'!$F:$F,"ספטמבר 2026") | AF5: =SUMIFS('כל ההוצאות'!$D:$D,'כל ההוצאות'!$B:$B,"Anthropic",'כל ההוצאות'!$F:$F,"אוקטובר 2026") | AG5: =SUMIFS('כל ההוצאות'!$E:$E,'כל ההוצאות'!$B:$B,"Anthropic",'כל ההוצאות'!$F:$F,"אוקטובר 2026") | AH5: =SUMIFS('כל ההוצאות'!$D:$D,'כל ההוצאות'!$B:$B,"Anthropic",'כל ההוצאות'!$F:$F,"נובמבר 2026") | AI5: =SUMIFS('כל ההוצאות'!$E:$E,'כל ההוצאות'!$B:$B,"Anthropic",'כל ההוצאות'!$F:$F,"נובמבר 2026") | AJ5: =SUMIFS('כל ההוצאות'!$D:$D,'כל ההוצאות'!$B:$B,"Anthropic",'כל ההוצאות'!$F:$F,"דצמבר 2026") | AK5: =SUMIFS('כל ההוצאות'!$E:$E,'כל ההוצאות'!$B:$B,"Anthropic",'כל ההוצאות'!$F:$F,"דצמבר 2026") | AL5: =SUM(B5,D5,F5,H5,J5,L5,N5,P5,R5,T5,V5,X5,Z5,AB5,AD5,AF5,AH5,AJ5) | AM5: =SUM(C5,E5,G5,I5,K5,M5,O5,Q5,S5,U5,W5,Y5,AA5,AC5,AE5,AG5,AI5,AK5)
A6: Astria | B6: =SUMIFS('כל ההוצאות'!$D:$D,'כל ההוצאות'!$B:$B,"Astria",'כל ההוצאות'!$F:$F,"יולי 2025") | C6: =SUMIFS('כל ההוצאות'!$E:$E,'כל ההוצאות'!$B:$B,"Astria",'כל ההוצאות'!$F:$F,"יולי 2025") | D6: =SUMIFS('כל ההוצאות'!$D:$D,'כל ההוצאות'!$B:$B,"Astria",'כל ההוצאות'!$F:$F,"אוגוסט 2025") | E6: =SUMIFS('כל ההוצאות'!$E:$E,'כל ההוצאות'!$B:$B,"Astria",'כל ההוצאות'!$F:$F,"אוגוסט 2025") | F6: =SUMIFS('כל ההוצאות'!$D:$D,'כל ההוצאות'!$B:$B,"Astria",'כל ההוצאות'!$F:$F,"ספטמבר 2025") | G6: =SUMIFS('כל ההוצאות'!$E:$E,'כל ההוצאות'!$B:$B,"Astria",'כל ההוצאות'!$F:$F,"ספטמבר 2025") | H6: =SUMIFS('כל ההוצאות'!$D:$D,'כל ההוצאות'!$B:$B,"Astria",'כל ההוצאות'!$F:$F,"אוקטובר 2025") | I6: =SUMIFS('כל ההוצאות'!$E:$E,'כל ההוצאות'!$B:$B,"Astria",'כל ההוצאות'!$F:$F,"אוקטובר 2025") | J6: =SUMIFS('כל ההוצאות'!$D:$D,'כל ההוצאות'!$B:$B,"Astria",'כל ההוצאות'!$F:$F,"נובמבר 2025") | K6: =SUMIFS('כל ההוצאות'!$E:$E,'כל ההוצאות'!$B:$B,"Astria",'כל ההוצאות'!$F:$F,"נובמבר 2025") | L6: =SUMIFS('כל ההוצאות'!$D:$D,'כל ההוצאות'!$B:$B,"Astria",'כל ההוצאות'!$F:$F,"דצמבר 2025") | M6: =SUMIFS('כל ההוצאות'!$E:$E,'כל ההוצאות'!$B:$B,"Astria",'כל ההוצאות'!$F:$F,"דצמבר 2025") | N6: =SUMIFS('כל ההוצאות'!$D:$D,'כל ההוצאות'!$B:$B,"Astria",'כל ההוצאות'!$F:$F,"ינואר 2026") | O6: =SUMIFS('כל ההוצאות'!$E:$E,'כל ההוצאות'!$B:$B,"Astria",'כל ההוצאות'!$F:$F,"ינואר 2026") | P6: =SUMIFS('כל ההוצאות'!$D:$D,'כל ההוצאות'!$B:$B,"Astria",'כל ההוצאות'!$F:$F,"פברואר 2026") | Q6: =SUMIFS('כל ההוצאות'!$E:$E,'כל ההוצאות'!$B:$B,"Astria",'כל ההוצאות'!$F:$F,"פברואר 2026") | R6: =SUMIFS('כל ההוצאות'!$D:$D,'כל ההוצאות'!$B:$B,"Astria",'כל ההוצאות'!$F:$F,"מרץ 2026") | S6: =SUMIFS('כל ההוצאות'!$E:$E,'כל ההוצאות'!$B:$B,"Astria",'כל ההוצאות'!$F:$F,"מרץ 2026") | T6: =SUMIFS('כל ההוצאות'!$D:$D,'כל ההוצאות'!$B:$B,"Astria",'כל ההוצאות'!$F:$F,"אפריל 2026") | U6: =SUMIFS('כל ההוצאות'!$E:$E,'כל ההוצאות'!$B:$B,"Astria",'כל ההוצאות'!$F:$F,"אפריל 2026") | V6: =SUMIFS('כל ההוצאות'!$D:$D,'כל ההוצאות'!$B:$B,"Astria",'כל ההוצאות'!$F:$F,"מאי 2026") | W6: =SUMIFS('כל ההוצאות'!$E:$E,'כל ההוצאות'!$B:$B,"Astria",'כל ההוצאות'!$F:$F,"מאי 2026") | X6: =SUMIFS('כל ההוצאות'!$D:$D,'כל ההוצאות'!$B:$B,"Astria",'כל ההוצאות'!$F:$F,"יוני 2026") | Y6: =SUMIFS('כל ההוצאות'!$E:$E,'כל ההוצאות'!$B:$B,"Astria",'כל ההוצאות'!$F:$F,"יוני 2026") | Z6: =SUMIFS('כל ההוצאות'!$D:$D,'כל ההוצאות'!$B:$B,"Astria",'כל ההוצאות'!$F:$F,"יולי 2026") | AA6: =SUMIFS('כל ההוצאות'!$E:$E,'כל ההוצאות'!$B:$B,"Astria",'כל ההוצאות'!$F:$F,"יולי 2026") | AB6: =SUMIFS('כל ההוצאות'!$D:$D,'כל ההוצאות'!$B:$B,"Astria",'כל ההוצאות'!$F:$F,"אוגוסט 2026") | AC6: =SUMIFS('כל ההוצאות'!$E:$E,'כל ההוצאות'!$B:$B,"Astria",'כל ההוצאות'!$F:$F,"אוגוסט 2026") | AD6: =SUMIFS('כל ההוצאות'!$D:$D,'כל ההוצאות'!$B:$B,"Astria",'כל ההוצאות'!$F:$F,"ספטמבר 2026") | AE6: =SUMIFS('כל ההוצאות'!$E:$E,'כל ההוצאות'!$B:$B,"Astria",'כל ההוצאות'!$F:$F,"ספטמבר 2026") | AF6: =SUMIFS('כל ההוצאות'!$D:$D,'כל ההוצאות'!$B:$B,"Astria",'כל ההוצאות'!$F:$F,"אוקטובר 2026") | AG6: =SUMIFS('כל ההוצאות'!$E:$E,'כל ההוצאות'!$B:$B,"Astria",'כל ההוצאות'!$F:$F,"אוקטובר 2026") | AH6: =SUMIFS('כל ההוצאות'!$D:$D,'כל ההוצאות'!$B:$B,"Astria",'כל ההוצאות'!$F:$F,"נובמבר 2026") | AI6: =SUMIFS('כל ההוצאות'!$E:$E,'כל ההוצאות'!$B:$B,"Astria",'כל ההוצאות'!$F:$F,"נובמבר 2026") | AJ6: =SUMIFS('כל ההוצאות'!$D:$D,'כל ההוצאות'!$B:$B,"Astria",'כל ההוצאות'!$F:$F,"דצמבר 2026") | AK6: =SUMIFS('כל ההוצאות'!$E:$E,'כל ההוצאות'!$B:$B,"Astria",'כל ההוצאות'!$F:$F,"דצמבר 2026") | AL6: =SUM(B6,D6,F6,H6,J6,L6,N6,P6,R6,T6,V6,X6,Z6,AB6,AD6,AF6,AH6,AJ6) | AM6: =SUM(C6,E6,G6,I6,K6,M6,O6,Q6,S6,U6,W6,Y6,AA6,AC6,AE6,AG6,AI6,AK6)
A7: CapCut | B7: =SUMIFS('כל ההוצאות'!$D:$D,'כל ההוצאות'!$B:$B,"CapCut",'כל ההוצאות'!$F:$F,"יולי 2025") | C7: =SUMIFS('כל ההוצאות'!$E:$E,'כל ההוצאות'!$B:$B,"CapCut",'כל ההוצאות'!$F:$F,"יולי 2025") | D7: =SUMIFS('כל ההוצאות'!$D:$D,'כל ההוצאות'!$B:$B,"CapCut",'כל ההוצאות'!$F:$F,"אוגוסט 2025") | E7: =SUMIFS('כל ההוצאות'!$E:$E,'כל ההוצאות'!$B:$B,"CapCut",'כל ההוצאות'!$F:$F,"אוגוסט 2025") | F7: =SUMIFS('כל ההוצאות'!$D:$D,'כל ההוצאות'!$B:$B,"CapCut",'כל ההוצאות'!$F:$F,"ספטמבר 2025") | G7: =SUMIFS('כל ההוצאות'!$E:$E,'כל ההוצאות'!$B:$B,"CapCut",'כל ההוצאות'!$F:$F,"ספטמבר 2025") | H7: =SUMIFS('כל ההוצאות'!$D:$D,'כל ההוצאות'!$B:$B,"CapCut",'כל ההוצאות'!$F:$F,"אוקטובר 2025") | I7: =SUMIFS('כל ההוצאות'!$E:$E,'כל ההוצאות'!$B:$B,"CapCut",'כל ההוצאות'!$F:$F,"אוקטובר 2025") | J7: =SUMIFS('כל ההוצאות'!$D:$D,'כל ההוצאות'!$B:$B,"CapCut",'כל ההוצאות'!$F:$F,"נובמבר 2025") | K7: =SUMIFS('כל ההוצאות'!$E:$E,'כל ההוצאות'!$B:$B,"CapCut",'כל ההוצאות'!$F:$F,"נובמבר 2025") | L7: =SUMIFS('כל ההוצאות'!$D:$D,'כל ההוצאות'!$B:$B,"CapCut",'כל ההוצאות'!$F:$F,"דצמבר 2025") | M7: =SUMIFS('כל ההוצאות'!$E:$E,'כל ההוצאות'!$B:$B,"CapCut",'כל ההוצאות'!$F:$F,"דצמבר 2025") | N7: =SUMIFS('כל ההוצאות'!$D:$D,'כל ההוצאות'!$B:$B,"CapCut",'כל ההוצאות'!$F:$F,"ינואר 2026") | O7: =SUMIFS('כל ההוצאות'!$E:$E,'כל ההוצאות'!$B:$B,"CapCut",'כל ההוצאות'!$F:$F,"ינואר 2026") | P7: =SUMIFS('כל ההוצאות'!$D:$D,'כל ההוצאות'!$B:$B,"CapCut",'כל ההוצאות'!$F:$F,"פברואר 2026") | Q7: =SUMIFS('כל ההוצאות'!$E:$E,'כל ההוצאות'!$B:$B,"CapCut",'כל ההוצאות'!$F:$F,"פברואר 2026") | R7: =SUMIFS('כל ההוצאות'!$D:$D,'כל ההוצאות'!$B:$B,"CapCut",'כל ההוצאות'!$F:$F,"מרץ 2026") | S7: =SUMIFS('כל ההוצאות'!$E:$E,'כל ההוצאות'!$B:$B,"CapCut",'כל ההוצאות'!$F:$F,"מרץ 2026") | T7: =SUMIFS('כל ההוצאות'!$D:$D,'כל ההוצאות'!$B:$B,"CapCut",'כל ההוצאות'!$F:$F,"אפריל 2026") | U7: =SUMIFS('כל ההוצאות'!$E:$E,'כל ההוצאות'!$B:$B,"CapCut",'כל ההוצאות'!$F:$F,"אפריל 2026") | V7: =SUMIFS('כל ההוצאות'!$D:$D,'כל ההוצאות'!$B:$B,"CapCut",'כל ההוצאות'!$F:$F,"מאי 2026") | W7: =SUMIFS('כל ההוצאות'!$E:$E,'כל ההוצאות'!$B:$B,"CapCut",'כל ההוצאות'!$F:$F,"מאי 2026") | X7: =SUMIFS('כל ההוצאות'!$D:$D,'כל ההוצאות'!$B:$B,"CapCut",'כל ההוצאות'!$F:$F,"יוני 2026") | Y7: =SUMIFS('כל ההוצאות'!$E:$E,'כל ההוצאות'!$B:$B,"CapCut",'כל ההוצאות'!$F:$F,"יוני 2026") | Z7: =SUMIFS('כל ההוצאות'!$D:$D,'כל ההוצאות'!$B:$B,"CapCut",'כל ההוצאות'!$F:$F,"יולי 2026") | AA7: =SUMIFS('כל ההוצאות'!$E:$E,'כל ההוצאות'!$B:$B,"CapCut",'כל ההוצאות'!$F:$F,"יולי 2026") | AB7: =SUMIFS('כל ההוצאות'!$D:$D,'כל ההוצאות'!$B:$B,"CapCut",'כל ההוצאות'!$F:$F,"אוגוסט 2026") | AC7: =SUMIFS('כל ההוצאות'!$E:$E,'כל ההוצאות'!$B:$B,"CapCut",'כל ההוצאות'!$F:$F,"אוגוסט 2026") | AD7: =SUMIFS('כל ההוצאות'!$D:$D,'כל ההוצאות'!$B:$B,"CapCut",'כל ההוצאות'!$F:$F,"ספטמבר 2026") | AE7: =SUMIFS('כל ההוצאות'!$E:$E,'כל ההוצאות'!$B:$B,"CapCut",'כל ההוצאות'!$F:$F,"ספטמבר 2026") | AF7: =SUMIFS('כל ההוצאות'!$D:$D,'כל ההוצאות'!$B:$B,"CapCut",'כל ההוצאות'!$F:$F,"אוקטובר 2026") | AG7: =SUMIFS('כל ההוצאות'!$E:$E,'כל ההוצאות'!$B:$B,"CapCut",'כל ההוצאות'!$F:$F,"אוקטובר 2026") | AH7: =SUMIFS('כל ההוצאות'!$D:$D,'כל ההוצאות'!$B:$B,"CapCut",'כל ההוצאות'!$F:$F,"נובמבר 2026") | AI7: =SUMIFS('כל ההוצאות'!$E:$E,'כל ההוצאות'!$B:$B,"CapCut",'כל ההוצאות'!$F:$F,"נובמבר 2026") | AJ7: =SUMIFS('כל ההוצאות'!$D:$D,'כל ההוצאות'!$B:$B,"CapCut",'כל ההוצאות'!$F:$F,"דצמבר 2026") | AK7: =SUMIFS('כל ההוצאות'!$E:$E,'כל ההוצאות'!$B:$B,"CapCut",'כל ההוצאות'!$F:$F,"דצמבר 2026") | AL7: =SUM(B7,D7,F7,H7,J7,L7,N7,P7,R7,T7,V7,X7,Z7,AB7,AD7,AF7,AH7,AJ7) | AM7: =SUM(C7,E7,G7,I7,K7,M7,O7,Q7,S7,U7,W7,Y7,AA7,AC7,AE7,AG7,AI7,AK7)
A8: Dzine | B8: =SUMIFS('כל ההוצאות'!$D:$D,'כל ההוצאות'!$B:$B,"Dzine",'כל ההוצאות'!$F:$F,"יולי 2025") | C8: =SUMIFS('כל ההוצאות'!$E:$E,'כל ההוצאות'!$B:$B,"Dzine",'כל ההוצאות'!$F:$F,"יולי 2025") | D8: =SUMIFS('כל ההוצאות'!$D:$D,'כל ההוצאות'!$B:$B,"Dzine",'כל ההוצאות'!$F:$F,"אוגוסט 2025") | E8: =SUMIFS('כל ההוצאות'!$E:$E,'כל ההוצאות'!$B:$B,"Dzine",'כל ההוצאות'!$F:$F,"אוגוסט 2025") | F8: =SUMIFS('כל ההוצאות'!$D:$D,'כל ההוצאות'!$B:$B,"Dzine",'כל ההוצאות'!$F:$F,"ספטמבר 2025") | G8: =SUMIFS('כל ההוצאות'!$E:$E,'כל ההוצאות'!$B:$B,"Dzine",'כל ההוצאות'!$F:$F,"ספטמבר 2025") | H8: =SUMIFS('כל ההוצאות'!$D:$D,'כל ההוצאות'!$B:$B,"Dzine",'כל ההוצאות'!$F:$F,"אוקטובר 2025") | I8: =SUMIFS('כל ההוצאות'!$E:$E,'כל ההוצאות'!$B:$B,"Dzine",'כל ההוצאות'!$F:$F,"אוקטובר 2025") | J8: =SUMIFS('כל ההוצאות'!$D:$D,'כל ההוצאות'!$B:$B,"Dzine",'כל ההוצאות'!$F:$F,"נובמבר 2025") | K8: =SUMIFS('כל ההוצאות'!$E:$E,'כל ההוצאות'!$B:$B,"Dzine",'כל ההוצאות'!$F:$F,"נובמבר 2025") | L8: =SUMIFS('כל ההוצאות'!$D:$D,'כל ההוצאות'!$B:$B,"Dzine",'כל ההוצאות'!$F:$F,"דצמבר 2025") | M8: =SUMIFS('כל ההוצאות'!$E:$E,'כל ההוצאות'!$B:$B,"Dzine",'כל ההוצאות'!$F:$F,"דצמבר 2025") | N8: =SUMIFS('כל ההוצאות'!$D:$D,'כל ההוצאות'!$B:$B,"Dzine",'כל ההוצאות'!$F:$F,"ינואר 2026") | O8: =SUMIFS('כל ההוצאות'!$E:$E,'כל ההוצאות'!$B:$B,"Dzine",'כל ההוצאות'!$F:$F,"ינואר 2026") | P8: =SUMIFS('כל ההוצאות'!$D:$D,'כל ההוצאות'!$B:$B,"Dzine",'כל ההוצאות'!$F:$F,"פברואר 2026") | Q8: =SUMIFS('כל ההוצאות'!$E:$E,'כל ההוצאות'!$B:$B,"Dzine",'כל ההוצאות'!$F:$F,"פברואר 2026") | R8: =SUMIFS('כל ההוצאות'!$D:$D,'כל ההוצאות'!$B:$B,"Dzine",'כל ההוצאות'!$F:$F,"מרץ 2026") | S8: =SUMIFS('כל ההוצאות'!$E:$E,'כל ההוצאות'!$B:$B,"Dzine",'כל ההוצאות'!$F:$F,"מרץ 2026") | T8: =SUMIFS('כל ההוצאות'!$D:$D,'כל ההוצאות'!$B:$B,"Dzine",'כל ההוצאות'!$F:$F,"אפריל 2026") | U8: =SUMIFS('כל ההוצאות'!$E:$E,'כל ההוצאות'!$B:$B,"Dzine",'כל ההוצאות'!$F:$F,"אפריל 2026") | V8: =SUMIFS('כל ההוצאות'!$D:$D,'כל ההוצאות'!$B:$B,"Dzine",'כל ההוצאות'!$F:$F,"מאי 2026") | W8: =SUMIFS('כל ההוצאות'!$E:$E,'כל ההוצאות'!$B:$B,"Dzine",'כל ההוצאות'!$F:$F,"מאי 2026") | X8: =SUMIFS('כל ההוצאות'!$D:$D,'כל ההוצאות'!$B:$B,"Dzine",'כל ההוצאות'!$F:$F,"יוני 2026") | Y8: =SUMIFS('כל ההוצאות'!$E:$E,'כל ההוצאות'!$B:$B,"Dzine",'כל ההוצאות'!$F:$F,"יוני 2026") | Z8: =SUMIFS('כל ההוצאות'!$D:$D,'כל ההוצאות'!$B:$B,"Dzine",'כל ההוצאות'!$F:$F,"יולי 2026") | AA8: =SUMIFS('כל ההוצאות'!$E:$E,'כל ההוצאות'!$B:$B,"Dzine",'כל ההוצאות'!$F:$F,"יולי 2026") | AB8: =SUMIFS('כל ההוצאות'!$D:$D,'כל ההוצאות'!$B:$B,"Dzine",'כל ההוצאות'!$F:$F,"אוגוסט 2026") | AC8: =SUMIFS('כל ההוצאות'!$E:$E,'כל ההוצאות'!$B:$B,"Dzine",'כל ההוצאות'!$F:$F,"אוגוסט 2026") | AD8: =SUMIFS('כל ההוצאות'!$D:$D,'כל ההוצאות'!$B:$B,"Dzine",'כל ההוצאות'!$F:$F,"ספטמבר 2026") | AE8: =SUMIFS('כל ההוצאות'!$E:$E,'כל ההוצאות'!$B:$B,"Dzine",'כל ההוצאות'!$F:$F,"ספטמבר 2026") | AF8: =SUMIFS('כל ההוצאות'!$D:$D,'כל ההוצאות'!$B:$B,"Dzine",'כל ההוצאות'!$F:$F,"אוקטובר 2026") | AG8: =SUMIFS('כל ההוצאות'!$E:$E,'כל ההוצאות'!$B:$B,"Dzine",'כל ההוצאות'!$F:$F,"אוקטובר 2026") | AH8: =SUMIFS('כל ההוצאות'!$D:$D,'כל ההוצאות'!$B:$B,"Dzine",'כל ההוצאות'!$F:$F,"נובמבר 2026") | AI8: =SUMIFS('כל ההוצאות'!$E:$E,'כל ההוצאות'!$B:$B,"Dzine",'כל ההוצאות'!$F:$F,"נובמבר 2026") | AJ8: =SUMIFS('כל ההוצאות'!$D:$D,'כל ההוצאות'!$B:$B,"Dzine",'כל ההוצאות'!$F:$F,"דצמבר 2026") | AK8: =SUMIFS('כל ההוצאות'!$E:$E,'כל ההוצאות'!$B:$B,"Dzine",'כל ההוצאות'!$F:$F,"דצמבר 2026") | AL8: =SUM(B8,D8,F8,H8,J8,L8,N8,P8,R8,T8,V8,X8,Z8,AB8,AD8,AF8,AH8,AJ8) | AM8: =SUM(C8,E8,G8,I8,K8,M8,O8,Q8,S8,U8,W8,Y8,AA8,AC8,AE8,AG8,AI8,AK8)
A9: Eleven Labs | B9: =SUMIFS('כל ההוצאות'!$D:$D,'כל ההוצאות'!$B:$B,"Eleven Labs",'כל ההוצאות'!$F:$F,"יולי 2025") | C9: =SUMIFS('כל ההוצאות'!$E:$E,'כל ההוצאות'!$B:$B,"Eleven Labs",'כל ההוצאות'!$F:$F,"יולי 2025") | D9: =SUMIFS('כל ההוצאות'!$D:$D,'כל ההוצאות'!$B:$B,"Eleven Labs",'כל ההוצאות'!$F:$F,"אוגוסט 2025") | E9: =SUMIFS('כל ההוצאות'!$E:$E,'כל ההוצאות'!$B:$B,"Eleven Labs",'כל ההוצאות'!$F:$F,"אוגוסט 2025") | F9: =SUMIFS('כל ההוצאות'!$D:$D,'כל ההוצאות'!$B:$B,"Eleven Labs",'כל ההוצאות'!$F:$F,"ספטמבר 2025") | G9: =SUMIFS('כל ההוצאות'!$E:$E,'כל ההוצאות'!$B:$B,"Eleven Labs",'כל ההוצאות'!$F:$F,"ספטמבר 2025") | H9: =SUMIFS('כל ההוצאות'!$D:$D,'כל ההוצאות'!$B:$B,"Eleven Labs",'כל ההוצאות'!$F:$F,"אוקטובר 2025") | I9: =SUMIFS('כל ההוצאות'!$E:$E,'כל ההוצאות'!$B:$B,"Eleven Labs",'כל ההוצאות'!$F:$F,"אוקטובר 2025") | J9: =SUMIFS('כל ההוצאות'!$D:$D,'כל ההוצאות'!$B:$B,"Eleven Labs",'כל ההוצאות'!$F:$F,"נובמבר 2025") | K9: =SUMIFS('כל ההוצאות'!$E:$E,'כל ההוצאות'!$B:$B,"Eleven Labs",'כל ההוצאות'!$F:$F,"נובמבר 2025") | L9: =SUMIFS('כל ההוצאות'!$D:$D,'כל ההוצאות'!$B:$B,"Eleven Labs",'כל ההוצאות'!$F:$F,"דצמבר 2025") | M9: =SUMIFS('כל ההוצאות'!$E:$E,'כל ההוצאות'!$B:$B,"Eleven Labs",'כל ההוצאות'!$F:$F,"דצמבר 2025") | N9: =SUMIFS('כל ההוצאות'!$D:$D,'כל ההוצאות'!$B:$B,"Eleven Labs",'כל ההוצאות'!$F:$F,"ינואר 2026") | O9: =SUMIFS('כל ההוצאות'!$E:$E,'כל ההוצאות'!$B:$B,"Eleven Labs",'כל ההוצאות'!$F:$F,"ינואר 2026") | P9: =SUMIFS('כל ההוצאות'!$D:$D,'כל ההוצאות'!$B:$B,"Eleven Labs",'כל ההוצאות'!$F:$F,"פברואר 2026") | Q9: =SUMIFS('כל ההוצאות'!$E:$E,'כל ההוצאות'!$B:$B,"Eleven Labs",'כל ההוצאות'!$F:$F,"פברואר 2026") | R9: =SUMIFS('כל ההוצאות'!$D:$D,'כל ההוצאות'!$B:$B,"Eleven Labs",'כל ההוצאות'!$F:$F,"מרץ 2026") | S9: =SUMIFS('כל ההוצאות'!$E:$E,'כל ההוצאות'!$B:$B,"Eleven Labs",'כל ההוצאות'!$F:$F,"מרץ 2026") | T9: =SUMIFS('כל ההוצאות'!$D:$D,'כל ההוצאות'!$B:$B,"Eleven Labs",'כל ההוצאות'!$F:$F,"אפריל 2026") | U9: =SUMIFS('כל ההוצאות'!$E:$E,'כל ההוצאות'!$B:$B,"Eleven Labs",'כל ההוצאות'!$F:$F,"אפריל 2026") | V9: =SUMIFS('כל ההוצאות'!$D:$D,'כל ההוצאות'!$B:$B,"Eleven Labs",'כל ההוצאות'!$F:$F,"מאי 2026") | W9: =SUMIFS('כל ההוצאות'!$E:$E,'כל ההוצאות'!$B:$B,"Eleven Labs",'כל ההוצאות'!$F:$F,"מאי 2026") | X9: =SUMIFS('כל ההוצאות'!$D:$D,'כל ההוצאות'!$B:$B,"Eleven Labs",'כל ההוצאות'!$F:$F,"יוני 2026") | Y9: =SUMIFS('כל ההוצאות'!$E:$E,'כל ההוצאות'!$B:$B,"Eleven Labs",'כל ההוצאות'!$F:$F,"יוני 2026") | Z9: =SUMIFS('כל ההוצאות'!$D:$D,'כל ההוצאות'!$B:$B,"Eleven Labs",'כל ההוצאות'!$F:$F,"יולי 2026") | AA9: =SUMIFS('כל ההוצאות'!$E:$E,'כל ההוצאות'!$B:$B,"Eleven Labs",'כל ההוצאות'!$F:$F,"יולי 2026") | AB9: =SUMIFS('כל ההוצאות'!$D:$D,'כל ההוצאות'!$B:$B,"Eleven Labs",'כל ההוצאות'!$F:$F,"אוגוסט 2026") | AC9: =SUMIFS('כל ההוצאות'!$E:$E,'כל ההוצאות'!$B:$B,"Eleven Labs",'כל ההוצאות'!$F:$F,"אוגוסט 2026") | AD9: =SUMIFS('כל ההוצאות'!$D:$D,'כל ההוצאות'!$B:$B,"Eleven Labs",'כל ההוצאות'!$F:$F,"ספטמבר 2026") | AE9: =SUMIFS('כל ההוצאות'!$E:$E,'כל ההוצאות'!$B:$B,"Eleven Labs",'כל ההוצאות'!$F:$F,"ספטמבר 2026") | AF9: =SUMIFS('כל ההוצאות'!$D:$D,'כל ההוצאות'!$B:$B,"Eleven Labs",'כל ההוצאות'!$F:$F,"אוקטובר 2026") | AG9: =SUMIFS('כל ההוצאות'!$E:$E,'כל ההוצאות'!$B:$B,"Eleven Labs",'כל ההוצאות'!$F:$F,"אוקטובר 2026") | AH9: =SUMIFS('כל ההוצאות'!$D:$D,'כל ההוצאות'!$B:$B,"Eleven Labs",'כל ההוצאות'!$F:$F,"נובמבר 2026") | AI9: =SUMIFS('כל ההוצאות'!$E:$E,'כל ההוצאות'!$B:$B,"Eleven Labs",'כל ההוצאות'!$F:$F,"נובמבר 2026") | AJ9: =SUMIFS('כל ההוצאות'!$D:$D,'כל ההוצאות'!$B:$B,"Eleven Labs",'כל ההוצאות'!$F:$F,"דצמבר 2026") | AK9: =SUMIFS('כל ההוצאות'!$E:$E,'כל ההוצאות'!$B:$B,"Eleven Labs",'כל ההוצאות'!$F:$F,"דצמבר 2026") | AL9: =SUM(B9,D9,F9,H9,J9,L9,N9,P9,R9,T9,V9,X9,Z9,AB9,AD9,AF9,AH9,AJ9) | AM9: =SUM(C9,E9,G9,I9,K9,M9,O9,Q9,S9,U9,W9,Y9,AA9,AC9,AE9,AG9,AI9,AK9)
A10: Genspark | B10: =SUMIFS('כל ההוצאות'!$D:$D,'כל ההוצאות'!$B:$B,"Genspark",'כל ההוצאות'!$F:$F,"יולי 2025") | C10: =SUMIFS('כל ההוצאות'!$E:$E,'כל ההוצאות'!$B:$B,"Genspark",'כל ההוצאות'!$F:$F,"יולי 2025") | D10: =SUMIFS('כל ההוצאות'!$D:$D,'כל ההוצאות'!$B:$B,"Genspark",'כל ההוצאות'!$F:$F,"אוגוסט 2025") | E10: =SUMIFS('כל ההוצאות'!$E:$E,'כל ההוצאות'!$B:$B,"Genspark",'כל ההוצאות'!$F:$F,"אוגוסט 2025") | F10: =SUMIFS('כל ההוצאות'!$D:$D,'כל ההוצאות'!$B:$B,"Genspark",'כל ההוצאות'!$F:$F,"ספטמבר 2025") | G10: =SUMIFS('כל ההוצאות'!$E:$E,'כל ההוצאות'!$B:$B,"Genspark",'כל ההוצאות'!$F:$F,"ספטמבר 2025") | H10: =SUMIFS('כל ההוצאות'!$D:$D,'כל ההוצאות'!$B:$B,"Genspark",'כל ההוצאות'!$F:$F,"אוקטובר 2025") | I10: =SUMIFS('כל ההוצאות'!$E:$E,'כל ההוצאות'!$B:$B,"Genspark",'כל ההוצאות'!$F:$F,"אוקטובר 2025") | J10: =SUMIFS('כל ההוצאות'!$D:$D,'כל ההוצאות'!$B:$B,"Genspark",'כל ההוצאות'!$F:$F,"נובמבר 2025") | K10: =SUMIFS('כל ההוצאות'!$E:$E,'כל ההוצאות'!$B:$B,"Genspark",'כל ההוצאות'!$F:$F,"נובמבר 2025") | L10: =SUMIFS('כל ההוצאות'!$D:$D,'כל ההוצאות'!$B:$B,"Genspark",'כל ההוצאות'!$F:$F,"דצמבר 2025") | M10: =SUMIFS('כל ההוצאות'!$E:$E,'כל ההוצאות'!$B:$B,"Genspark",'כל ההוצאות'!$F:$F,"דצמבר 2025") | N10: =SUMIFS('כל ההוצאות'!$D:$D,'כל ההוצאות'!$B:$B,"Genspark",'כל ההוצאות'!$F:$F,"ינואר 2026") | O10: =SUMIFS('כל ההוצאות'!$E:$E,'כל ההוצאות'!$B:$B,"Genspark",'כל ההוצאות'!$F:$F,"ינואר 2026") | P10: =SUMIFS('כל ההוצאות'!$D:$D,'כל ההוצאות'!$B:$B,"Genspark",'כל ההוצאות'!$F:$F,"פברואר 2026") | Q10: =SUMIFS('כל ההוצאות'!$E:$E,'כל ההוצאות'!$B:$B,"Genspark",'כל ההוצאות'!$F:$F,"פברואר 2026") | R10: =SUMIFS('כל ההוצאות'!$D:$D,'כל ההוצאות'!$B:$B,"Genspark",'כל ההוצאות'!$F:$F,"מרץ 2026") | S10: =SUMIFS('כל ההוצאות'!$E:$E,'כל ההוצאות'!$B:$B,"Genspark",'כל ההוצאות'!$F:$F,"מרץ 2026") | T10: =SUMIFS('כל ההוצאות'!$D:$D,'כל ההוצאות'!$B:$B,"Genspark",'כל ההוצאות'!$F:$F,"אפריל 2026") | U10: =SUMIFS('כל ההוצאות'!$E:$E,'כל ההוצאות'!$B:$B,"Genspark",'כל ההוצאות'!$F:$F,"אפריל 2026") | V10: =SUMIFS('כל ההוצאות'!$D:$D,'כל ההוצאות'!$B:$B,"Genspark",'כל ההוצאות'!$F:$F,"מאי 2026") | W10: =SUMIFS('כל ההוצאות'!$E:$E,'כל ההוצאות'!$B:$B,"Genspark",'כל ההוצאות'!$F:$F,"מאי 2026") | X10: =SUMIFS('כל ההוצאות'!$D:$D,'כל ההוצאות'!$B:$B,"Genspark",'כל ההוצאות'!$F:$F,"יוני 2026") | Y10: =SUMIFS('כל ההוצאות'!$E:$E,'כל ההוצאות'!$B:$B,"Genspark",'כל ההוצאות'!$F:$F,"יוני 2026") | Z10: =SUMIFS('כל ההוצאות'!$D:$D,'כל ההוצאות'!$B:$B,"Genspark",'כל ההוצאות'!$F:$F,"יולי 2026") | AA10: =SUMIFS('כל ההוצאות'!$E:$E,'כל ההוצאות'!$B:$B,"Genspark",'כל ההוצאות'!$F:$F,"יולי 2026") | AB10: =SUMIFS('כל ההוצאות'!$D:$D,'כל ההוצאות'!$B:$B,"Genspark",'כל ההוצאות'!$F:$F,"אוגוסט 2026") | AC10: =SUMIFS('כל ההוצאות'!$E:$E,'כל ההוצאות'!$B:$B,"Genspark",'כל ההוצאות'!$F:$F,"אוגוסט 2026") | AD10: =SUMIFS('כל ההוצאות'!$D:$D,'כל ההוצאות'!$B:$B,"Genspark",'כל ההוצאות'!$F:$F,"ספטמבר 2026") | AE10: =SUMIFS('כל ההוצאות'!$E:$E,'כל ההוצאות'!$B:$B,"Genspark",'כל ההוצאות'!$F:$F,"ספטמבר 2026") | AF10: =SUMIFS('כל ההוצאות'!$D:$D,'כל ההוצאות'!$B:$B,"Genspark",'כל ההוצאות'!$F:$F,"אוקטובר 2026") | AG10: =SUMIFS('כל ההוצאות'!$E:$E,'כל ההוצאות'!$B:$B,"Genspark",'כל ההוצאות'!$F:$F,"אוקטובר 2026") | AH10: =SUMIFS('כל ההוצאות'!$D:$D,'כל ההוצאות'!$B:$B,"Genspark",'כל ההוצאות'!$F:$F,"נובמבר 2026") | AI10: =SUMIFS('כל ההוצאות'!$E:$E,'כל ההוצאות'!$B:$B,"Genspark",'כל ההוצאות'!$F:$F,"נובמבר 2026") | AJ10: =SUMIFS('כל ההוצאות'!$D:$D,'כל ההוצאות'!$B:$B,"Genspark",'כל ההוצאות'!$F:$F,"דצמבר 2026") | AK10: =SUMIFS('כל ההוצאות'!$E:$E,'כל ההוצאות'!$B:$B,"Genspark",'כל ההוצאות'!$F:$F,"דצמבר 2026") | AL10: =SUM(B10,D10,F10,H10,J10,L10,N10,P10,R10,T10,V10,X10,Z10,AB10,AD10,AF10,AH10,AJ10) | AM10: =SUM(C10,E10,G10,I10,K10,M10,O10,Q10,S10,U10,W10,Y10,AA10,AC10,AE10,AG10,AI10,AK10)
A11: Google Cloud | B11: =SUMIFS('כל ההוצאות'!$D:$D,'כל ההוצאות'!$B:$B,"Google Cloud",'כל ההוצאות'!$F:$F,"יולי 2025") | C11: =SUMIFS('כל ההוצאות'!$E:$E,'כל ההוצאות'!$B:$B,"Google Cloud",'כל ההוצאות'!$F:$F,"יולי 2025") | D11: =SUMIFS('כל ההוצאות'!$D:$D,'כל ההוצאות'!$B:$B,"Google Cloud",'כל ההוצאות'!$F:$F,"אוגוסט 2025") | E11: =SUMIFS('כל ההוצאות'!$E:$E,'כל ההוצאות'!$B:$B,"Google Cloud",'כל ההוצאות'!$F:$F,"אוגוסט 2025") | F11: =SUMIFS('כל ההוצאות'!$D:$D,'כל ההוצאות'!$B:$B,"Google Cloud",'כל ההוצאות'!$F:$F,"ספטמבר 2025") | G11: =SUMIFS('כל ההוצאות'!$E:$E,'כל ההוצאות'!$B:$B,"Google Cloud",'כל ההוצאות'!$F:$F,"ספטמבר 2025") | H11: =SUMIFS('כל ההוצאות'!$D:$D,'כל ההוצאות'!$B:$B,"Google Cloud",'כל ההוצאות'!$F:$F,"אוקטובר 2025") | I11: =SUMIFS('כל ההוצאות'!$E:$E,'כל ההוצאות'!$B:$B,"Google Cloud",'כל ההוצאות'!$F:$F,"אוקטובר 2025") | J11: =SUMIFS('כל ההוצאות'!$D:$D,'כל ההוצאות'!$B:$B,"Google Cloud",'כל ההוצאות'!$F:$F,"נובמבר 2025") | K11: =SUMIFS('כל ההוצאות'!$E:$E,'כל ההוצאות'!$B:$B,"Google Cloud",'כל ההוצאות'!$F:$F,"נובמבר 2025") | L11: =SUMIFS('כל ההוצאות'!$D:$D,'כל ההוצאות'!$B:$B,"Google Cloud",'כל ההוצאות'!$F:$F,"דצמבר 2025") | M11: =SUMIFS('כל ההוצאות'!$E:$E,'כל ההוצאות'!$B:$B,"Google Cloud",'כל ההוצאות'!$F:$F,"דצמבר 2025") | N11: =SUMIFS('כל ההוצאות'!$D:$D,'כל ההוצאות'!$B:$B,"Google Cloud",'כל ההוצאות'!$F:$F,"ינואר 2026") | O11: =SUMIFS('כל ההוצאות'!$E:$E,'כל ההוצאות'!$B:$B,"Google Cloud",'כל ההוצאות'!$F:$F,"ינואר 2026") | P11: =SUMIFS('כל ההוצאות'!$D:$D,'כל ההוצאות'!$B:$B,"Google Cloud",'כל ההוצאות'!$F:$F,"פברואר 2026") | Q11: =SUMIFS('כל ההוצאות'!$E:$E,'כל ההוצאות'!$B:$B,"Google Cloud",'כל ההוצאות'!$F:$F,"פברואר 2026") | R11: =SUMIFS('כל ההוצאות'!$D:$D,'כל ההוצאות'!$B:$B,"Google Cloud",'כל ההוצאות'!$F:$F,"מרץ 2026") | S11: =SUMIFS('כל ההוצאות'!$E:$E,'כל ההוצאות'!$B:$B,"Google Cloud",'כל ההוצאות'!$F:$F,"מרץ 2026") | T11: =SUMIFS('כל ההוצאות'!$D:$D,'כל ההוצאות'!$B:$B,"Google Cloud",'כל ההוצאות'!$F:$F,"אפריל 2026") | U11: =SUMIFS('כל ההוצאות'!$E:$E,'כל ההוצאות'!$B:$B,"Google Cloud",'כל ההוצאות'!$F:$F,"אפריל 2026") | V11: =SUMIFS('כל ההוצאות'!$D:$D,'כל ההוצאות'!$B:$B,"Google Cloud",'כל ההוצאות'!$F:$F,"מאי 2026") | W11: =SUMIFS('כל ההוצאות'!$E:$E,'כל ההוצאות'!$B:$B,"Google Cloud",'כל ההוצאות'!$F:$F,"מאי 2026") | X11: =SUMIFS('כל ההוצאות'!$D:$D,'כל ההוצאות'!$B:$B,"Google Cloud",'כל ההוצאות'!$F:$F,"יוני 2026") | Y11: =SUMIFS('כל ההוצאות'!$E:$E,'כל ההוצאות'!$B:$B,"Google Cloud",'כל ההוצאות'!$F:$F,"יוני 2026") | Z11: =SUMIFS('כל ההוצאות'!$D:$D,'כל ההוצאות'!$B:$B,"Google Cloud",'כל ההוצאות'!$F:$F,"יולי 2026") | AA11: =SUMIFS('כל ההוצאות'!$E:$E,'כל ההוצאות'!$B:$B,"Google Cloud",'כל ההוצאות'!$F:$F,"יולי 2026") | AB11: =SUMIFS('כל ההוצאות'!$D:$D,'כל ההוצאות'!$B:$B,"Google Cloud",'כל ההוצאות'!$F:$F,"אוגוסט 2026") | AC11: =SUMIFS('כל ההוצאות'!$E:$E,'כל ההוצאות'!$B:$B,"Google Cloud",'כל ההוצאות'!$F:$F,"אוגוסט 2026") | AD11: =SUMIFS('כל ההוצאות'!$D:$D,'כל ההוצאות'!$B:$B,"Google Cloud",'כל ההוצאות'!$F:$F,"ספטמבר 2026") | AE11: =SUMIFS('כל ההוצאות'!$E:$E,'כל ההוצאות'!$B:$B,"Google Cloud",'כל ההוצאות'!$F:$F,"ספטמבר 2026") | AF11: =SUMIFS('כל ההוצאות'!$D:$D,'כל ההוצאות'!$B:$B,"Google Cloud",'כל ההוצאות'!$F:$F,"אוקטובר 2026") | AG11: =SUMIFS('כל ההוצאות'!$E:$E,'כל ההוצאות'!$B:$B,"Google Cloud",'כל ההוצאות'!$F:$F,"אוקטובר 2026") | AH11: =SUMIFS('כל ההוצאות'!$D:$D,'כל ההוצאות'!$B:$B,"Google Cloud",'כל ההוצאות'!$F:$F,"נובמבר 2026") | AI11: =SUMIFS('כל ההוצאות'!$E:$E,'כל ההוצאות'!$B:$B,"Google Cloud",'כל ההוצאות'!$F:$F,"נובמבר 2026") | AJ11: =SUMIFS('כל ההוצאות'!$D:$D,'כל ההוצאות'!$B:$B,"Google Cloud",'כל ההוצאות'!$F:$F,"דצמבר 2026") | AK11: =SUMIFS('כל ההוצאות'!$E:$E,'כל ההוצאות'!$B:$B,"Google Cloud",'כל ההוצאות'!$F:$F,"דצמבר 2026") | AL11: =SUM(B11,D11,F11,H11,J11,L11,N11,P11,R11,T11,V11,X11,Z11,AB11,AD11,AF11,AH11,AJ11) | AM11: =SUM(C11,E11,G11,I11,K11,M11,O11,Q11,S11,U11,W11,Y11,AA11,AC11,AE11,AG11,AI11,AK11)
A12: Google Workspace | B12: =SUMIFS('כל ההוצאות'!$D:$D,'כל ההוצאות'!$B:$B,"Google Workspace",'כל ההוצאות'!$F:$F,"יולי 2025") | C12: =SUMIFS('כל ההוצאות'!$E:$E,'כל ההוצאות'!$B:$B,"Google Workspace",'כל ההוצאות'!$F:$F,"יולי 2025") | D12: =SUMIFS('כל ההוצאות'!$D:$D,'כל ההוצאות'!$B:$B,"Google Workspace",'כל ההוצאות'!$F:$F,"אוגוסט 2025") | E12: =SUMIFS('כל ההוצאות'!$E:$E,'כל ההוצאות'!$B:$B,"Google Workspace",'כל ההוצאות'!$F:$F,"אוגוסט 2025") | F12: =SUMIFS('כל ההוצאות'!$D:$D,'כל ההוצאות'!$B:$B,"Google Workspace",'כל ההוצאות'!$F:$F,"ספטמבר 2025") | G12: =SUMIFS('כל ההוצאות'!$E:$E,'כל ההוצאות'!$B:$B,"Google Workspace",'כל ההוצאות'!$F:$F,"ספטמבר 2025") | H12: =SUMIFS('כל ההוצאות'!$D:$D,'כל ההוצאות'!$B:$B,"Google Workspace",'כל ההוצאות'!$F:$F,"אוקטובר 2025") | I12: =SUMIFS('כל ההוצאות'!$E:$E,'כל ההוצאות'!$B:$B,"Google Workspace",'כל ההוצאות'!$F:$F,"אוקטובר 2025") | J12: =SUMIFS('כל ההוצאות'!$D:$D,'כל ההוצאות'!$B:$B,"Google Workspace",'כל ההוצאות'!$F:$F,"נובמבר 2025") | K12: =SUMIFS('כל ההוצאות'!$E:$E,'כל ההוצאות'!$B:$B,"Google Workspace",'כל ההוצאות'!$F:$F,"נובמבר 2025") | L12: =SUMIFS('כל ההוצאות'!$D:$D,'כל ההוצאות'!$B:$B,"Google Workspace",'כל ההוצאות'!$F:$F,"דצמבר 2025") | M12: =SUMIFS('כל ההוצאות'!$E:$E,'כל ההוצאות'!$B:$B,"Google Workspace",'כל ההוצאות'!$F:$F,"דצמבר 2025") | N12: =SUMIFS('כל ההוצאות'!$D:$D,'כל ההוצאות'!$B:$B,"Google Workspace",'כל ההוצאות'!$F:$F,"ינואר 2026") | O12: =SUMIFS('כל ההוצאות'!$E:$E,'כל ההוצאות'!$B:$B,"Google Workspace",'כל ההוצאות'!$F:$F,"ינואר 2026") | P12: =SUMIFS('כל ההוצאות'!$D:$D,'כל ההוצאות'!$B:$B,"Google Workspace",'כל ההוצאות'!$F:$F,"פברואר 2026") | Q12: =SUMIFS('כל ההוצאות'!$E:$E,'כל ההוצאות'!$B:$B,"Google Workspace",'כל ההוצאות'!$F:$F,"פברואר 2026") | R12: =SUMIFS('כל ההוצאות'!$D:$D,'כל ההוצאות'!$B:$B,"Google Workspace",'כל ההוצאות'!$F:$F,"מרץ 2026") | S12: =SUMIFS('כל ההוצאות'!$E:$E,'כל ההוצאות'!$B:$B,"Google Workspace",'כל ההוצאות'!$F:$F,"מרץ 2026") | T12: =SUMIFS('כל ההוצאות'!$D:$D,'כל ההוצאות'!$B:$B,"Google Workspace",'כל ההוצאות'!$F:$F,"אפריל 2026") | U12: =SUMIFS('כל ההוצאות'!$E:$E,'כל ההוצאות'!$B:$B,"Google Workspace",'כל ההוצאות'!$F:$F,"אפריל 2026") | V12: =SUMIFS('כל ההוצאות'!$D:$D,'כל ההוצאות'!$B:$B,"Google Workspace",'כל ההוצאות'!$F:$F,"מאי 2026") | W12: =SUMIFS('כל ההוצאות'!$E:$E,'כל ההוצאות'!$B:$B,"Google Workspace",'כל ההוצאות'!$F:$F,"מאי 2026") | X12: =SUMIFS('כל ההוצאות'!$D:$D,'כל ההוצאות'!$B:$B,"Google Workspace",'כל ההוצאות'!$F:$F,"יוני 2026") | Y12: =SUMIFS('כל ההוצאות'!$E:$E,'כל ההוצאות'!$B:$B,"Google Workspace",'כל ההוצאות'!$F:$F,"יוני 2026") | Z12: =SUMIFS('כל ההוצאות'!$D:$D,'כל ההוצאות'!$B:$B,"Google Workspace",'כל ההוצאות'!$F:$F,"יולי 2026") | AA12: =SUMIFS('כל ההוצאות'!$E:$E,'כל ההוצאות'!$B:$B,"Google Workspace",'כל ההוצאות'!$F:$F,"יולי 2026") | AB12: =SUMIFS('כל ההוצאות'!$D:$D,'כל ההוצאות'!$B:$B,"Google Workspace",'כל ההוצאות'!$F:$F,"אוגוסט 2026") | AC12: =SUMIFS('כל ההוצאות'!$E:$E,'כל ההוצאות'!$B:$B,"Google Workspace",'כל ההוצאות'!$F:$F,"אוגוסט 2026") | AD12: =SUMIFS('כל ההוצאות'!$D:$D,'כל ההוצאות'!$B:$B,"Google Workspace",'כל ההוצאות'!$F:$F,"ספטמבר 2026") | AE12: =SUMIFS('כל ההוצאות'!$E:$E,'כל ההוצאות'!$B:$B,"Google Workspace",'כל ההוצאות'!$F:$F,"ספטמבר 2026") | AF12: =SUMIFS('כל ההוצאות'!$D:$D,'כל ההוצאות'!$B:$B,"Google Workspace",'כל ההוצאות'!$F:$F,"אוקטובר 2026") | AG12: =SUMIFS('כל ההוצאות'!$E:$E,'כל ההוצאות'!$B:$B,"Google Workspace",'כל ההוצאות'!$F:$F,"אוקטובר 2026") | AH12: =SUMIFS('כל ההוצאות'!$D:$D,'כל ההוצאות'!$B:$B,"Google Workspace",'כל ההוצאות'!$F:$F,"נובמבר 2026") | AI12: =SUMIFS('כל ההוצאות'!$E:$E,'כל ההוצאות'!$B:$B,"Google Workspace",'כל ההוצאות'!$F:$F,"נובמבר 2026") | AJ12: =SUMIFS('כל ההוצאות'!$D:$D,'כל ההוצאות'!$B:$B,"Google Workspace",'כל ההוצאות'!$F:$F,"דצמבר 2026") | AK12: =SUMIFS('כל ההוצאות'!$E:$E,'כל ההוצאות'!$B:$B,"Google Workspace",'כל ההוצאות'!$F:$F,"דצמבר 2026") | AL12: =SUM(B12,D12,F12,H12,J12,L12,N12,P12,R12,T12,V12,X12,Z12,AB12,AD12,AF12,AH12,AJ12) | AM12: =SUM(C12,E12,G12,I12,K12,M12,O12,Q12,S12,U12,W12,Y12,AA12,AC12,AE12,AG12,AI12,AK12)
A13: Hedra | B13: =SUMIFS('כל ההוצאות'!$D:$D,'כל ההוצאות'!$B:$B,"Hedra",'כל ההוצאות'!$F:$F,"יולי 2025") | C13: =SUMIFS('כל ההוצאות'!$E:$E,'כל ההוצאות'!$B:$B,"Hedra",'כל ההוצאות'!$F:$F,"יולי 2025") | D13: =SUMIFS('כל ההוצאות'!$D:$D,'כל ההוצאות'!$B:$B,"Hedra",'כל ההוצאות'!$F:$F,"אוגוסט 2025") | E13: =SUMIFS('כל ההוצאות'!$E:$E,'כל ההוצאות'!$B:$B,"Hedra",'כל ההוצאות'!$F:$F,"אוגוסט 2025") | F13: =SUMIFS('כל ההוצאות'!$D:$D,'כל ההוצאות'!$B:$B,"Hedra",'כל ההוצאות'!$F:$F,"ספטמבר 2025") | G13: =SUMIFS('כל ההוצאות'!$E:$E,'כל ההוצאות'!$B:$B,"Hedra",'כל ההוצאות'!$F:$F,"ספטמבר 2025") | H13: =SUMIFS('כל ההוצאות'!$D:$D,'כל ההוצאות'!$B:$B,"Hedra",'כל ההוצאות'!$F:$F,"אוקטובר 2025") | I13: =SUMIFS('כל ההוצאות'!$E:$E,'כל ההוצאות'!$B:$B,"Hedra",'כל ההוצאות'!$F:$F,"אוקטובר 2025") | J13: =SUMIFS('כל ההוצאות'!$D:$D,'כל ההוצאות'!$B:$B,"Hedra",'כל ההוצאות'!$F:$F,"נובמבר 2025") | K13: =SUMIFS('כל ההוצאות'!$E:$E,'כל ההוצאות'!$B:$B,"Hedra",'כל ההוצאות'!$F:$F,"נובמבר 2025") | L13: =SUMIFS('כל ההוצאות'!$D:$D,'כל ההוצאות'!$B:$B,"Hedra",'כל ההוצאות'!$F:$F,"דצמבר 2025") | M13: =SUMIFS('כל ההוצאות'!$E:$E,'כל ההוצאות'!$B:$B,"Hedra",'כל ההוצאות'!$F:$F,"דצמבר 2025") | N13: =SUMIFS('כל ההוצאות'!$D:$D,'כל ההוצאות'!$B:$B,"Hedra",'כל ההוצאות'!$F:$F,"ינואר 2026") | O13: =SUMIFS('כל ההוצאות'!$E:$E,'כל ההוצאות'!$B:$B,"Hedra",'כל ההוצאות'!$F:$F,"ינואר 2026") | P13: =SUMIFS('כל ההוצאות'!$D:$D,'כל ההוצאות'!$B:$B,"Hedra",'כל ההוצאות'!$F:$F,"פברואר 2026") | Q13: =SUMIFS('כל ההוצאות'!$E:$E,'כל ההוצאות'!$B:$B,"Hedra",'כל ההוצאות'!$F:$F,"פברואר 2026") | R13: =SUMIFS('כל ההוצאות'!$D:$D,'כל ההוצאות'!$B:$B,"Hedra",'כל ההוצאות'!$F:$F,"מרץ 2026") | S13: =SUMIFS('כל ההוצאות'!$E:$E,'כל ההוצאות'!$B:$B,"Hedra",'כל ההוצאות'!$F:$F,"מרץ 2026") | T13: =SUMIFS('כל ההוצאות'!$D:$D,'כל ההוצאות'!$B:$B,"Hedra",'כל ההוצאות'!$F:$F,"אפריל 2026") | U13: =SUMIFS('כל ההוצאות'!$E:$E,'כל ההוצאות'!$B:$B,"Hedra",'כל ההוצאות'!$F:$F,"אפריל 2026") | V13: =SUMIFS('כל ההוצאות'!$D:$D,'כל ההוצאות'!$B:$B,"Hedra",'כל ההוצאות'!$F:$F,"מאי 2026") | W13: =SUMIFS('כל ההוצאות'!$E:$E,'כל ההוצאות'!$B:$B,"Hedra",'כל ההוצאות'!$F:$F,"מאי 2026") | X13: =SUMIFS('כל ההוצאות'!$D:$D,'כל ההוצאות'!$B:$B,"Hedra",'כל ההוצאות'!$F:$F,"יוני 2026") | Y13: =SUMIFS('כל ההוצאות'!$E:$E,'כל ההוצאות'!$B:$B,"Hedra",'כל ההוצאות'!$F:$F,"יוני 2026") | Z13: =SUMIFS('כל ההוצאות'!$D:$D,'כל ההוצאות'!$B:$B,"Hedra",'כל ההוצאות'!$F:$F,"יולי 2026") | AA13: =SUMIFS('כל ההוצאות'!$E:$E,'כל ההוצאות'!$B:$B,"Hedra",'כל ההוצאות'!$F:$F,"יולי 2026") | AB13: =SUMIFS('כל ההוצאות'!$D:$D,'כל ההוצאות'!$B:$B,"Hedra",'כל ההוצאות'!$F:$F,"אוגוסט 2026") | AC13: =SUMIFS('כל ההוצאות'!$E:$E,'כל ההוצאות'!$B:$B,"Hedra",'כל ההוצאות'!$F:$F,"אוגוסט 2026") | AD13: =SUMIFS('כל ההוצאות'!$D:$D,'כל ההוצאות'!$B:$B,"Hedra",'כל ההוצאות'!$F:$F,"ספטמבר 2026") | AE13: =SUMIFS('כל ההוצאות'!$E:$E,'כל ההוצאות'!$B:$B,"Hedra",'כל ההוצאות'!$F:$F,"ספטמבר 2026") | AF13: =SUMIFS('כל ההוצאות'!$D:$D,'כל ההוצאות'!$B:$B,"Hedra",'כל ההוצאות'!$F:$F,"אוקטובר 2026") | AG13: =SUMIFS('כל ההוצאות'!$E:$E,'כל ההוצאות'!$B:$B,"Hedra",'כל ההוצאות'!$F:$F,"אוקטובר 2026") | AH13: =SUMIFS('כל ההוצאות'!$D:$D,'כל ההוצאות'!$B:$B,"Hedra",'כל ההוצאות'!$F:$F,"נובמבר 2026") | AI13: =SUMIFS('כל ההוצאות'!$E:$E,'כל ההוצאות'!$B:$B,"Hedra",'כל ההוצאות'!$F:$F,"נובמבר 2026") | AJ13: =SUMIFS('כל ההוצאות'!$D:$D,'כל ההוצאות'!$B:$B,"Hedra",'כל ההוצאות'!$F:$F,"דצמבר 2026") | AK13: =SUMIFS('כל ההוצאות'!$E:$E,'כל ההוצאות'!$B:$B,"Hedra",'כל ההוצאות'!$F:$F,"דצמבר 2026") | AL13: =SUM(B13,D13,F13,H13,J13,L13,N13,P13,R13,T13,V13,X13,Z13,AB13,AD13,AF13,AH13,AJ13) | AM13: =SUM(C13,E13,G13,I13,K13,M13,O13,Q13,S13,U13,W13,Y13,AA13,AC13,AE13,AG13,AI13,AK13)
A14: Higgsfield | B14: =SUMIFS('כל ההוצאות'!$D:$D,'כל ההוצאות'!$B:$B,"Higgsfield",'כל ההוצאות'!$F:$F,"יולי 2025") | C14: =SUMIFS('כל ההוצאות'!$E:$E,'כל ההוצאות'!$B:$B,"Higgsfield",'כל ההוצאות'!$F:$F,"יולי 2025") | D14: =SUMIFS('כל ההוצאות'!$D:$D,'כל ההוצאות'!$B:$B,"Higgsfield",'כל ההוצאות'!$F:$F,"אוגוסט 2025") | E14: =SUMIFS('כל ההוצאות'!$E:$E,'כל ההוצאות'!$B:$B,"Higgsfield",'כל ההוצאות'!$F:$F,"אוגוסט 2025") | F14: =SUMIFS('כל ההוצאות'!$D:$D,'כל ההוצאות'!$B:$B,"Higgsfield",'כל ההוצאות'!$F:$F,"ספטמבר 2025") | G14: =SUMIFS('כל ההוצאות'!$E:$E,'כל ההוצאות'!$B:$B,"Higgsfield",'כל ההוצאות'!$F:$F,"ספטמבר 2025") | H14: =SUMIFS('כל ההוצאות'!$D:$D,'כל ההוצאות'!$B:$B,"Higgsfield",'כל ההוצאות'!$F:$F,"אוקטובר 2025") | I14: =SUMIFS('כל ההוצאות'!$E:$E,'כל ההוצאות'!$B:$B,"Higgsfield",'כל ההוצאות'!$F:$F,"אוקטובר 2025") | J14: =SUMIFS('כל ההוצאות'!$D:$D,'כל ההוצאות'!$B:$B,"Higgsfield",'כל ההוצאות'!$F:$F,"נובמבר 2025") | K14: =SUMIFS('כל ההוצאות'!$E:$E,'כל ההוצאות'!$B:$B,"Higgsfield",'כל ההוצאות'!$F:$F,"נובמבר 2025") | L14: =SUMIFS('כל ההוצאות'!$D:$D,'כל ההוצאות'!$B:$B,"Higgsfield",'כל ההוצאות'!$F:$F,"דצמבר 2025") | M14: =SUMIFS('כל ההוצאות'!$E:$E,'כל ההוצאות'!$B:$B,"Higgsfield",'כל ההוצאות'!$F:$F,"דצמבר 2025") | N14: =SUMIFS('כל ההוצאות'!$D:$D,'כל ההוצאות'!$B:$B,"Higgsfield",'כל ההוצאות'!$F:$F,"ינואר 2026") | O14: =SUMIFS('כל ההוצאות'!$E:$E,'כל ההוצאות'!$B:$B,"Higgsfield",'כל ההוצאות'!$F:$F,"ינואר 2026") | P14: =SUMIFS('כל ההוצאות'!$D:$D,'כל ההוצאות'!$B:$B,"Higgsfield",'כל ההוצאות'!$F:$F,"פברואר 2026") | Q14: =SUMIFS('כל ההוצאות'!$E:$E,'כל ההוצאות'!$B:$B,"Higgsfield",'כל ההוצאות'!$F:$F,"פברואר 2026") | R14: =SUMIFS('כל ההוצאות'!$D:$D,'כל ההוצאות'!$B:$B,"Higgsfield",'כל ההוצאות'!$F:$F,"מרץ 2026") | S14: =SUMIFS('כל ההוצאות'!$E:$E,'כל ההוצאות'!$B:$B,"Higgsfield",'כל ההוצאות'!$F:$F,"מרץ 2026") | T14: =SUMIFS('כל ההוצאות'!$D:$D,'כל ההוצאות'!$B:$B,"Higgsfield",'כל ההוצאות'!$F:$F,"אפריל 2026") | U14: =SUMIFS('כל ההוצאות'!$E:$E,'כל ההוצאות'!$B:$B,"Higgsfield",'כל ההוצאות'!$F:$F,"אפריל 2026") | V14: =SUMIFS('כל ההוצאות'!$D:$D,'כל ההוצאות'!$B:$B,"Higgsfield",'כל ההוצאות'!$F:$F,"מאי 2026") | W14: =SUMIFS('כל ההוצאות'!$E:$E,'כל ההוצאות'!$B:$B,"Higgsfield",'כל ההוצאות'!$F:$F,"מאי 2026") | X14: =SUMIFS('כל ההוצאות'!$D:$D,'כל ההוצאות'!$B:$B,"Higgsfield",'כל ההוצאות'!$F:$F,"יוני 2026") | Y14: =SUMIFS('כל ההוצאות'!$E:$E,'כל ההוצאות'!$B:$B,"Higgsfield",'כל ההוצאות'!$F:$F,"יוני 2026") | Z14: =SUMIFS('כל ההוצאות'!$D:$D,'כל ההוצאות'!$B:$B,"Higgsfield",'כל ההוצאות'!$F:$F,"יולי 2026") | AA14: =SUMIFS('כל ההוצאות'!$E:$E,'כל ההוצאות'!$B:$B,"Higgsfield",'כל ההוצאות'!$F:$F,"יולי 2026") | AB14: =SUMIFS('כל ההוצאות'!$D:$D,'כל ההוצאות'!$B:$B,"Higgsfield",'כל ההוצאות'!$F:$F,"אוגוסט 2026") | AC14: =SUMIFS('כל ההוצאות'!$E:$E,'כל ההוצאות'!$B:$B,"Higgsfield",'כל ההוצאות'!$F:$F,"אוגוסט 2026") | AD14: =SUMIFS('כל ההוצאות'!$D:$D,'כל ההוצאות'!$B:$B,"Higgsfield",'כל ההוצאות'!$F:$F,"ספטמבר 2026") | AE14: =SUMIFS('כל ההוצאות'!$E:$E,'כל ההוצאות'!$B:$B,"Higgsfield",'כל ההוצאות'!$F:$F,"ספטמבר 2026") | AF14: =SUMIFS('כל ההוצאות'!$D:$D,'כל ההוצאות'!$B:$B,"Higgsfield",'כל ההוצאות'!$F:$F,"אוקטובר 2026") | AG14: =SUMIFS('כל ההוצאות'!$E:$E,'כל ההוצאות'!$B:$B,"Higgsfield",'כל ההוצאות'!$F:$F,"אוקטובר 2026") | AH14: =SUMIFS('כל ההוצאות'!$D:$D,'כל ההוצאות'!$B:$B,"Higgsfield",'כל ההוצאות'!$F:$F,"נובמבר 2026") | AI14: =SUMIFS('כל ההוצאות'!$E:$E,'כל ההוצאות'!$B:$B,"Higgsfield",'כל ההוצאות'!$F:$F,"נובמבר 2026") | AJ14: =SUMIFS('כל ההוצאות'!$D:$D,'כל ההוצאות'!$B:$B,"Higgsfield",'כל ההוצאות'!$F:$F,"דצמבר 2026") | AK14: =SUMIFS('כל ההוצאות'!$E:$E,'כל ההוצאות'!$B:$B,"Higgsfield",'כל ההוצאות'!$F:$F,"דצמבר 2026") | AL14: =SUM(B14,D14,F14,H14,J14,L14,N14,P14,R14,T14,V14,X14,Z14,AB14,AD14,AF14,AH14,AJ14) | AM14: =SUM(C14,E14,G14,I14,K14,M14,O14,Q14,S14,U14,W14,Y14,AA14,AC14,AE14,AG14,AI14,AK14)
A15: IONOS | B15: =SUMIFS('כל ההוצאות'!$D:$D,'כל ההוצאות'!$B:$B,"IONOS",'כל ההוצאות'!$F:$F,"יולי 2025") | C15: =SUMIFS('כל ההוצאות'!$E:$E,'כל ההוצאות'!$B:$B,"IONOS",'כל ההוצאות'!$F:$F,"יולי 2025") | D15: =SUMIFS('כל ההוצאות'!$D:$D,'כל ההוצאות'!$B:$B,"IONOS",'כל ההוצאות'!$F:$F,"אוגוסט 2025") | E15: =SUMIFS('כל ההוצאות'!$E:$E,'כל ההוצאות'!$B:$B,"IONOS",'כל ההוצאות'!$F:$F,"אוגוסט 2025") | F15: =SUMIFS('כל ההוצאות'!$D:$D,'כל ההוצאות'!$B:$B,"IONOS",'כל ההוצאות'!$F:$F,"ספטמבר 2025") | G15: =SUMIFS('כל ההוצאות'!$E:$E,'כל ההוצאות'!$B:$B,"IONOS",'כל ההוצאות'!$F:$F,"ספטמבר 2025") | H15: =SUMIFS('כל ההוצאות'!$D:$D,'כל ההוצאות'!$B:$B,"IONOS",'כל ההוצאות'!$F:$F,"אוקטובר 2025") | I15: =SUMIFS('כל ההוצאות'!$E:$E,'כל ההוצאות'!$B:$B,"IONOS",'כל ההוצאות'!$F:$F,"אוקטובר 2025") | J15: =SUMIFS('כל ההוצאות'!$D:$D,'כל ההוצאות'!$B:$B,"IONOS",'כל ההוצאות'!$F:$F,"נובמבר 2025") | K15: =SUMIFS('כל ההוצאות'!$E:$E,'כל ההוצאות'!$B:$B,"IONOS",'כל ההוצאות'!$F:$F,"נובמבר 2025") | L15: =SUMIFS('כל ההוצאות'!$D:$D,'כל ההוצאות'!$B:$B,"IONOS",'כל ההוצאות'!$F:$F,"דצמבר 2025") | M15: =SUMIFS('כל ההוצאות'!$E:$E,'כל ההוצאות'!$B:$B,"IONOS",'כל ההוצאות'!$F:$F,"דצמבר 2025") | N15: =SUMIFS('כל ההוצאות'!$D:$D,'כל ההוצאות'!$B:$B,"IONOS",'כל ההוצאות'!$F:$F,"ינואר 2026") | O15: =SUMIFS('כל ההוצאות'!$E:$E,'כל ההוצאות'!$B:$B,"IONOS",'כל ההוצאות'!$F:$F,"ינואר 2026") | P15: =SUMIFS('כל ההוצאות'!$D:$D,'כל ההוצאות'!$B:$B,"IONOS",'כל ההוצאות'!$F:$F,"פברואר 2026") | Q15: =SUMIFS('כל ההוצאות'!$E:$E,'כל ההוצאות'!$B:$B,"IONOS",'כל ההוצאות'!$F:$F,"פברואר 2026") | R15: =SUMIFS('כל ההוצאות'!$D:$D,'כל ההוצאות'!$B:$B,"IONOS",'כל ההוצאות'!$F:$F,"מרץ 2026") | S15: =SUMIFS('כל ההוצאות'!$E:$E,'כל ההוצאות'!$B:$B,"IONOS",'כל ההוצאות'!$F:$F,"מרץ 2026") | T15: =SUMIFS('כל ההוצאות'!$D:$D,'כל ההוצאות'!$B:$B,"IONOS",'כל ההוצאות'!$F:$F,"אפריל 2026") | U15: =SUMIFS('כל ההוצאות'!$E:$E,'כל ההוצאות'!$B:$B,"IONOS",'כל ההוצאות'!$F:$F,"אפריל 2026") | V15: =SUMIFS('כל ההוצאות'!$D:$D,'כל ההוצאות'!$B:$B,"IONOS",'כל ההוצאות'!$F:$F,"מאי 2026") | W15: =SUMIFS('כל ההוצאות'!$E:$E,'כל ההוצאות'!$B:$B,"IONOS",'כל ההוצאות'!$F:$F,"מאי 2026") | X15: =SUMIFS('כל ההוצאות'!$D:$D,'כל ההוצאות'!$B:$B,"IONOS",'כל ההוצאות'!$F:$F,"יוני 2026") | Y15: =SUMIFS('כל ההוצאות'!$E:$E,'כל ההוצאות'!$B:$B,"IONOS",'כל ההוצאות'!$F:$F,"יוני 2026") | Z15: =SUMIFS('כל ההוצאות'!$D:$D,'כל ההוצאות'!$B:$B,"IONOS",'כל ההוצאות'!$F:$F,"יולי 2026") | AA15: =SUMIFS('כל ההוצאות'!$E:$E,'כל ההוצאות'!$B:$B,"IONOS",'כל ההוצאות'!$F:$F,"יולי 2026") | AB15: =SUMIFS('כל ההוצאות'!$D:$D,'כל ההוצאות'!$B:$B,"IONOS",'כל ההוצאות'!$F:$F,"אוגוסט 2026") | AC15: =SUMIFS('כל ההוצאות'!$E:$E,'כל ההוצאות'!$B:$B,"IONOS",'כל ההוצאות'!$F:$F,"אוגוסט 2026") | AD15: =SUMIFS('כל ההוצאות'!$D:$D,'כל ההוצאות'!$B:$B,"IONOS",'כל ההוצאות'!$F:$F,"ספטמבר 2026") | AE15: =SUMIFS('כל ההוצאות'!$E:$E,'כל ההוצאות'!$B:$B,"IONOS",'כל ההוצאות'!$F:$F,"ספטמבר 2026") | AF15: =SUMIFS('כל ההוצאות'!$D:$D,'כל ההוצאות'!$B:$B,"IONOS",'כל ההוצאות'!$F:$F,"אוקטובר 2026") | AG15: =SUMIFS('כל ההוצאות'!$E:$E,'כל ההוצאות'!$B:$B,"IONOS",'כל ההוצאות'!$F:$F,"אוקטובר 2026") | AH15: =SUMIFS('כל ההוצאות'!$D:$D,'כל ההוצאות'!$B:$B,"IONOS",'כל ההוצאות'!$F:$F,"נובמבר 2026") | AI15: =SUMIFS('כל ההוצאות'!$E:$E,'כל ההוצאות'!$B:$B,"IONOS",'כל ההוצאות'!$F:$F,"נובמבר 2026") | AJ15: =SUMIFS('כל ההוצאות'!$D:$D,'כל ההוצאות'!$B:$B,"IONOS",'כל ההוצאות'!$F:$F,"דצמבר 2026") | AK15: =SUMIFS('כל ההוצאות'!$E:$E,'כל ההוצאות'!$B:$B,"IONOS",'כל ההוצאות'!$F:$F,"דצמבר 2026") | AL15: =SUM(B15,D15,F15,H15,J15,L15,N15,P15,R15,T15,V15,X15,Z15,AB15,AD15,AF15,AH15,AJ15) | AM15: =SUM(C15,E15,G15,I15,K15,M15,O15,Q15,S15,U15,W15,Y15,AA15,AC15,AE15,AG15,AI15,AK15)
A16: Ideogram AI | B16: =SUMIFS('כל ההוצאות'!$D:$D,'כל ההוצאות'!$B:$B,"Ideogram AI",'כל ההוצאות'!$F:$F,"יולי 2025") | C16: =SUMIFS('כל ההוצאות'!$E:$E,'כל ההוצאות'!$B:$B,"Ideogram AI",'כל ההוצאות'!$F:$F,"יולי 2025") | D16: =SUMIFS('כל ההוצאות'!$D:$D,'כל ההוצאות'!$B:$B,"Ideogram AI",'כל ההוצאות'!$F:$F,"אוגוסט 2025") | E16: =SUMIFS('כל ההוצאות'!$E:$E,'כל ההוצאות'!$B:$B,"Ideogram AI",'כל ההוצאות'!$F:$F,"אוגוסט 2025") | F16: =SUMIFS('כל ההוצאות'!$D:$D,'כל ההוצאות'!$B:$B,"Ideogram AI",'כל ההוצאות'!$F:$F,"ספטמבר 2025") | G16: =SUMIFS('כל ההוצאות'!$E:$E,'כל ההוצאות'!$B:$B,"Ideogram AI",'כל ההוצאות'!$F:$F,"ספטמבר 2025") | H16: =SUMIFS('כל ההוצאות'!$D:$D,'כל ההוצאות'!$B:$B,"Ideogram AI",'כל ההוצאות'!$F:$F,"אוקטובר 2025") | I16: =SUMIFS('כל ההוצאות'!$E:$E,'כל ההוצאות'!$B:$B,"Ideogram AI",'כל ההוצאות'!$F:$F,"אוקטובר 2025") | J16: =SUMIFS('כל ההוצאות'!$D:$D,'כל ההוצאות'!$B:$B,"Ideogram AI",'כל ההוצאות'!$F:$F,"נובמבר 2025") | K16: =SUMIFS('כל ההוצאות'!$E:$E,'כל ההוצאות'!$B:$B,"Ideogram AI",'כל ההוצאות'!$F:$F,"נובמבר 2025") | L16: =SUMIFS('כל ההוצאות'!$D:$D,'כל ההוצאות'!$B:$B,"Ideogram AI",'כל ההוצאות'!$F:$F,"דצמבר 2025") | M16: =SUMIFS('כל ההוצאות'!$E:$E,'כל ההוצאות'!$B:$B,"Ideogram AI",'כל ההוצאות'!$F:$F,"דצמבר 2025") | N16: =SUMIFS('כל ההוצאות'!$D:$D,'כל ההוצאות'!$B:$B,"Ideogram AI",'כל ההוצאות'!$F:$F,"ינואר 2026") | O16: =SUMIFS('כל ההוצאות'!$E:$E,'כל ההוצאות'!$B:$B,"Ideogram AI",'כל ההוצאות'!$F:$F,"ינואר 2026") | P16: =SUMIFS('כל ההוצאות'!$D:$D,'כל ההוצאות'!$B:$B,"Ideogram AI",'כל ההוצאות'!$F:$F,"פברואר 2026") | Q16: =SUMIFS('כל ההוצאות'!$E:$E,'כל ההוצאות'!$B:$B,"Ideogram AI",'כל ההוצאות'!$F:$F,"פברואר 2026") | R16: =SUMIFS('כל ההוצאות'!$D:$D,'כל ההוצאות'!$B:$B,"Ideogram AI",'כל ההוצאות'!$F:$F,"מרץ 2026") | S16: =SUMIFS('כל ההוצאות'!$E:$E,'כל ההוצאות'!$B:$B,"Ideogram AI",'כל ההוצאות'!$F:$F,"מרץ 2026") | T16: =SUMIFS('כל ההוצאות'!$D:$D,'כל ההוצאות'!$B:$B,"Ideogram AI",'כל ההוצאות'!$F:$F,"אפריל 2026") | U16: =SUMIFS('כל ההוצאות'!$E:$E,'כל ההוצאות'!$B:$B,"Ideogram AI",'כל ההוצאות'!$F:$F,"אפריל 2026") | V16: =SUMIFS('כל ההוצאות'!$D:$D,'כל ההוצאות'!$B:$B,"Ideogram AI",'כל ההוצאות'!$F:$F,"מאי 2026") | W16: =SUMIFS('כל ההוצאות'!$E:$E,'כל ההוצאות'!$B:$B,"Ideogram AI",'כל ההוצאות'!$F:$F,"מאי 2026") | X16: =SUMIFS('כל ההוצאות'!$D:$D,'כל ההוצאות'!$B:$B,"Ideogram AI",'כל ההוצאות'!$F:$F,"יוני 2026") | Y16: =SUMIFS('כל ההוצאות'!$E:$E,'כל ההוצאות'!$B:$B,"Ideogram AI",'כל ההוצאות'!$F:$F,"יוני 2026") | Z16: =SUMIFS('כל ההוצאות'!$D:$D,'כל ההוצאות'!$B:$B,"Ideogram AI",'כל ההוצאות'!$F:$F,"יולי 2026") | AA16: =SUMIFS('כל ההוצאות'!$E:$E,'כל ההוצאות'!$B:$B,"Ideogram AI",'כל ההוצאות'!$F:$F,"יולי 2026") | AB16: =SUMIFS('כל ההוצאות'!$D:$D,'כל ההוצאות'!$B:$B,"Ideogram AI",'כל ההוצאות'!$F:$F,"אוגוסט 2026") | AC16: =SUMIFS('כל ההוצאות'!$E:$E,'כל ההוצאות'!$B:$B,"Ideogram AI",'כל ההוצאות'!$F:$F,"אוגוסט 2026") | AD16: =SUMIFS('כל ההוצאות'!$D:$D,'כל ההוצאות'!$B:$B,"Ideogram AI",'כל ההוצאות'!$F:$F,"ספטמבר 2026") | AE16: =SUMIFS('כל ההוצאות'!$E:$E,'כל ההוצאות'!$B:$B,"Ideogram AI",'כל ההוצאות'!$F:$F,"ספטמבר 2026") | AF16: =SUMIFS('כל ההוצאות'!$D:$D,'כל ההוצאות'!$B:$B,"Ideogram AI",'כל ההוצאות'!$F:$F,"אוקטובר 2026") | AG16: =SUMIFS('כל ההוצאות'!$E:$E,'כל ההוצאות'!$B:$B,"Ideogram AI",'כל ההוצאות'!$F:$F,"אוקטובר 2026") | AH16: =SUMIFS('כל ההוצאות'!$D:$D,'כל ההוצאות'!$B:$B,"Ideogram AI",'כל ההוצאות'!$F:$F,"נובמבר 2026") | AI16: =SUMIFS('כל ההוצאות'!$E:$E,'כל ההוצאות'!$B:$B,"Ideogram AI",'כל ההוצאות'!$F:$F,"נובמבר 2026") | AJ16: =SUMIFS('כל ההוצאות'!$D:$D,'כל ההוצאות'!$B:$B,"Ideogram AI",'כל ההוצאות'!$F:$F,"דצמבר 2026") | AK16: =SUMIFS('כל ההוצאות'!$E:$E,'כל ההוצאות'!$B:$B,"Ideogram AI",'כל ההוצאות'!$F:$F,"דצמבר 2026") | AL16: =SUM(B16,D16,F16,H16,J16,L16,N16,P16,R16,T16,V16,X16,Z16,AB16,AD16,AF16,AH16,AJ16) | AM16: =SUM(C16,E16,G16,I16,K16,M16,O16,Q16,S16,U16,W16,Y16,AA16,AC16,AE16,AG16,AI16,AK16)
A17: Lovable | B17: =SUMIFS('כל ההוצאות'!$D:$D,'כל ההוצאות'!$B:$B,"Lovable",'כל ההוצאות'!$F:$F,"יולי 2025") | C17: =SUMIFS('כל ההוצאות'!$E:$E,'כל ההוצאות'!$B:$B,"Lovable",'כל ההוצאות'!$F:$F,"יולי 2025") | D17: =SUMIFS('כל ההוצאות'!$D:$D,'כל ההוצאות'!$B:$B,"Lovable",'כל ההוצאות'!$F:$F,"אוגוסט 2025") | E17: =SUMIFS('כל ההוצאות'!$E:$E,'כל ההוצאות'!$B:$B,"Lovable",'כל ההוצאות'!$F:$F,"אוגוסט 2025") | F17: =SUMIFS('כל ההוצאות'!$D:$D,'כל ההוצאות'!$B:$B,"Lovable",'כל ההוצאות'!$F:$F,"ספטמבר 2025") | G17: =SUMIFS('כל ההוצאות'!$E:$E,'כל ההוצאות'!$B:$B,"Lovable",'כל ההוצאות'!$F:$F,"ספטמבר 2025") | H17: =SUMIFS('כל ההוצאות'!$D:$D,'כל ההוצאות'!$B:$B,"Lovable",'כל ההוצאות'!$F:$F,"אוקטובר 2025") | I17: =SUMIFS('כל ההוצאות'!$E:$E,'כל ההוצאות'!$B:$B,"Lovable",'כל ההוצאות'!$F:$F,"אוקטובר 2025") | J17: =SUMIFS('כל ההוצאות'!$D:$D,'כל ההוצאות'!$B:$B,"Lovable",'כל ההוצאות'!$F:$F,"נובמבר 2025") | K17: =SUMIFS('כל ההוצאות'!$E:$E,'כל ההוצאות'!$B:$B,"Lovable",'כל ההוצאות'!$F:$F,"נובמבר 2025") | L17: =SUMIFS('כל ההוצאות'!$D:$D,'כל ההוצאות'!$B:$B,"Lovable",'כל ההוצאות'!$F:$F,"דצמבר 2025") | M17: =SUMIFS('כל ההוצאות'!$E:$E,'כל ההוצאות'!$B:$B,"Lovable",'כל ההוצאות'!$F:$F,"דצמבר 2025") | N17: =SUMIFS('כל ההוצאות'!$D:$D,'כל ההוצאות'!$B:$B,"Lovable",'כל ההוצאות'!$F:$F,"ינואר 2026") | O17: =SUMIFS('כל ההוצאות'!$E:$E,'כל ההוצאות'!$B:$B,"Lovable",'כל ההוצאות'!$F:$F,"ינואר 2026") | P17: =SUMIFS('כל ההוצאות'!$D:$D,'כל ההוצאות'!$B:$B,"Lovable",'כל ההוצאות'!$F:$F,"פברואר 2026") | Q17: =SUMIFS('כל ההוצאות'!$E:$E,'כל ההוצאות'!$B:$B,"Lovable",'כל ההוצאות'!$F:$F,"פברואר 2026") | R17: =SUMIFS('כל ההוצאות'!$D:$D,'כל ההוצאות'!$B:$B,"Lovable",'כל ההוצאות'!$F:$F,"מרץ 2026") | S17: =SUMIFS('כל ההוצאות'!$E:$E,'כל ההוצאות'!$B:$B,"Lovable",'כל ההוצאות'!$F:$F,"מרץ 2026") | T17: =SUMIFS('כל ההוצאות'!$D:$D,'כל ההוצאות'!$B:$B,"Lovable",'כל ההוצאות'!$F:$F,"אפריל 2026") | U17: =SUMIFS('כל ההוצאות'!$E:$E,'כל ההוצאות'!$B:$B,"Lovable",'כל ההוצאות'!$F:$F,"אפריל 2026") | V17: =SUMIFS('כל ההוצאות'!$D:$D,'כל ההוצאות'!$B:$B,"Lovable",'כל ההוצאות'!$F:$F,"מאי 2026") | W17: =SUMIFS('כל ההוצאות'!$E:$E,'כל ההוצאות'!$B:$B,"Lovable",'כל ההוצאות'!$F:$F,"מאי 2026") | X17: =SUMIFS('כל ההוצאות'!$D:$D,'כל ההוצאות'!$B:$B,"Lovable",'כל ההוצאות'!$F:$F,"יוני 2026") | Y17: =SUMIFS('כל ההוצאות'!$E:$E,'כל ההוצאות'!$B:$B,"Lovable",'כל ההוצאות'!$F:$F,"יוני 2026") | Z17: =SUMIFS('כל ההוצאות'!$D:$D,'כל ההוצאות'!$B:$B,"Lovable",'כל ההוצאות'!$F:$F,"יולי 2026") | AA17: =SUMIFS('כל ההוצאות'!$E:$E,'כל ההוצאות'!$B:$B,"Lovable",'כל ההוצאות'!$F:$F,"יולי 2026") | AB17: =SUMIFS('כל ההוצאות'!$D:$D,'כל ההוצאות'!$B:$B,"Lovable",'כל ההוצאות'!$F:$F,"אוגוסט 2026") | AC17: =SUMIFS('כל ההוצאות'!$E:$E,'כל ההוצאות'!$B:$B,"Lovable",'כל ההוצאות'!$F:$F,"אוגוסט 2026") | AD17: =SUMIFS('כל ההוצאות'!$D:$D,'כל ההוצאות'!$B:$B,"Lovable",'כל ההוצאות'!$F:$F,"ספטמבר 2026") | AE17: =SUMIFS('כל ההוצאות'!$E:$E,'כל ההוצאות'!$B:$B,"Lovable",'כל ההוצאות'!$F:$F,"ספטמבר 2026") | AF17: =SUMIFS('כל ההוצאות'!$D:$D,'כל ההוצאות'!$B:$B,"Lovable",'כל ההוצאות'!$F:$F,"אוקטובר 2026") | AG17: =SUMIFS('כל ההוצאות'!$E:$E,'כל ההוצאות'!$B:$B,"Lovable",'כל ההוצאות'!$F:$F,"אוקטובר 2026") | AH17: =SUMIFS('כל ההוצאות'!$D:$D,'כל ההוצאות'!$B:$B,"Lovable",'כל ההוצאות'!$F:$F,"נובמבר 2026") | AI17: =SUMIFS('כל ההוצאות'!$E:$E,'כל ההוצאות'!$B:$B,"Lovable",'כל ההוצאות'!$F:$F,"נובמבר 2026") | AJ17: =SUMIFS('כל ההוצאות'!$D:$D,'כל ההוצאות'!$B:$B,"Lovable",'כל ההוצאות'!$F:$F,"דצמבר 2026") | AK17: =SUMIFS('כל ההוצאות'!$E:$E,'כל ההוצאות'!$B:$B,"Lovable",'כל ההוצאות'!$F:$F,"דצמבר 2026") | AL17: =SUM(B17,D17,F17,H17,J17,L17,N17,P17,R17,T17,V17,X17,Z17,AB17,AD17,AF17,AH17,AJ17) | AM17: =SUM(C17,E17,G17,I17,K17,M17,O17,Q17,S17,U17,W17,Y17,AA17,AC17,AE17,AG17,AI17,AK17)
A18: Make | B18: =SUMIFS('כל ההוצאות'!$D:$D,'כל ההוצאות'!$B:$B,"Make",'כל ההוצאות'!$F:$F,"יולי 2025") | C18: =SUMIFS('כל ההוצאות'!$E:$E,'כל ההוצאות'!$B:$B,"Make",'כל ההוצאות'!$F:$F,"יולי 2025") | D18: =SUMIFS('כל ההוצאות'!$D:$D,'כל ההוצאות'!$B:$B,"Make",'כל ההוצאות'!$F:$F,"אוגוסט 2025") | E18: =SUMIFS('כל ההוצאות'!$E:$E,'כל ההוצאות'!$B:$B,"Make",'כל ההוצאות'!$F:$F,"אוגוסט 2025") | F18: =SUMIFS('כל ההוצאות'!$D:$D,'כל ההוצאות'!$B:$B,"Make",'כל ההוצאות'!$F:$F,"ספטמבר 2025") | G18: =SUMIFS('כל ההוצאות'!$E:$E,'כל ההוצאות'!$B:$B,"Make",'כל ההוצאות'!$F:$F,"ספטמבר 2025") | H18: =SUMIFS('כל ההוצאות'!$D:$D,'כל ההוצאות'!$B:$B,"Make",'כל ההוצאות'!$F:$F,"אוקטובר 2025") | I18: =SUMIFS('כל ההוצאות'!$E:$E,'כל ההוצאות'!$B:$B,"Make",'כל ההוצאות'!$F:$F,"אוקטובר 2025") | J18: =SUMIFS('כל ההוצאות'!$D:$D,'כל ההוצאות'!$B:$B,"Make",'כל ההוצאות'!$F:$F,"נובמבר 2025") | K18: =SUMIFS('כל ההוצאות'!$E:$E,'כל ההוצאות'!$B:$B,"Make",'כל ההוצאות'!$F:$F,"נובמבר 2025") | L18: =SUMIFS('כל ההוצאות'!$D:$D,'כל ההוצאות'!$B:$B,"Make",'כל ההוצאות'!$F:$F,"דצמבר 2025") | M18: =SUMIFS('כל ההוצאות'!$E:$E,'כל ההוצאות'!$B:$B,"Make",'כל ההוצאות'!$F:$F,"דצמבר 2025") | N18: =SUMIFS('כל ההוצאות'!$D:$D,'כל ההוצאות'!$B:$B,"Make",'כל ההוצאות'!$F:$F,"ינואר 2026") | O18: =SUMIFS('כל ההוצאות'!$E:$E,'כל ההוצאות'!$B:$B,"Make",'כל ההוצאות'!$F:$F,"ינואר 2026") | P18: =SUMIFS('כל ההוצאות'!$D:$D,'כל ההוצאות'!$B:$B,"Make",'כל ההוצאות'!$F:$F,"פברואר 2026") | Q18: =SUMIFS('כל ההוצאות'!$E:$E,'כל ההוצאות'!$B:$B,"Make",'כל ההוצאות'!$F:$F,"פברואר 2026") | R18: =SUMIFS('כל ההוצאות'!$D:$D,'כל ההוצאות'!$B:$B,"Make",'כל ההוצאות'!$F:$F,"מרץ 2026") | S18: =SUMIFS('כל ההוצאות'!$E:$E,'כל ההוצאות'!$B:$B,"Make",'כל ההוצאות'!$F:$F,"מרץ 2026") | T18: =SUMIFS('כל ההוצאות'!$D:$D,'כל ההוצאות'!$B:$B,"Make",'כל ההוצאות'!$F:$F,"אפריל 2026") | U18: =SUMIFS('כל ההוצאות'!$E:$E,'כל ההוצאות'!$B:$B,"Make",'כל ההוצאות'!$F:$F,"אפריל 2026") | V18: =SUMIFS('כל ההוצאות'!$D:$D,'כל ההוצאות'!$B:$B,"Make",'כל ההוצאות'!$F:$F,"מאי 2026") | W18: =SUMIFS('כל ההוצאות'!$E:$E,'כל ההוצאות'!$B:$B,"Make",'כל ההוצאות'!$F:$F,"מאי 2026") | X18: =SUMIFS('כל ההוצאות'!$D:$D,'כל ההוצאות'!$B:$B,"Make",'כל ההוצאות'!$F:$F,"יוני 2026") | Y18: =SUMIFS('כל ההוצאות'!$E:$E,'כל ההוצאות'!$B:$B,"Make",'כל ההוצאות'!$F:$F,"יוני 2026") | Z18: =SUMIFS('כל ההוצאות'!$D:$D,'כל ההוצאות'!$B:$B,"Make",'כל ההוצאות'!$F:$F,"יולי 2026") | AA18: =SUMIFS('כל ההוצאות'!$E:$E,'כל ההוצאות'!$B:$B,"Make",'כל ההוצאות'!$F:$F,"יולי 2026") | AB18: =SUMIFS('כל ההוצאות'!$D:$D,'כל ההוצאות'!$B:$B,"Make",'כל ההוצאות'!$F:$F,"אוגוסט 2026") | AC18: =SUMIFS('כל ההוצאות'!$E:$E,'כל ההוצאות'!$B:$B,"Make",'כל ההוצאות'!$F:$F,"אוגוסט 2026") | AD18: =SUMIFS('כל ההוצאות'!$D:$D,'כל ההוצאות'!$B:$B,"Make",'כל ההוצאות'!$F:$F,"ספטמבר 2026") | AE18: =SUMIFS('כל ההוצאות'!$E:$E,'כל ההוצאות'!$B:$B,"Make",'כל ההוצאות'!$F:$F,"ספטמבר 2026") | AF18: =SUMIFS('כל ההוצאות'!$D:$D,'כל ההוצאות'!$B:$B,"Make",'כל ההוצאות'!$F:$F,"אוקטובר 2026") | AG18: =SUMIFS('כל ההוצאות'!$E:$E,'כל ההוצאות'!$B:$B,"Make",'כל ההוצאות'!$F:$F,"אוקטובר 2026") | AH18: =SUMIFS('כל ההוצאות'!$D:$D,'כל ההוצאות'!$B:$B,"Make",'כל ההוצאות'!$F:$F,"נובמבר 2026") | AI18: =SUMIFS('כל ההוצאות'!$E:$E,'כל ההוצאות'!$B:$B,"Make",'כל ההוצאות'!$F:$F,"נובמבר 2026") | AJ18: =SUMIFS('כל ההוצאות'!$D:$D,'כל ההוצאות'!$B:$B,"Make",'כל ההוצאות'!$F:$F,"דצמבר 2026") | AK18: =SUMIFS('כל ההוצאות'!$E:$E,'כל ההוצאות'!$B:$B,"Make",'כל ההוצאות'!$F:$F,"דצמבר 2026") | AL18: =SUM(B18,D18,F18,H18,J18,L18,N18,P18,R18,T18,V18,X18,Z18,AB18,AD18,AF18,AH18,AJ18) | AM18: =SUM(C18,E18,G18,I18,K18,M18,O18,Q18,S18,U18,W18,Y18,AA18,AC18,AE18,AG18,AI18,AK18)
A19: Manus AI | B19: =SUMIFS('כל ההוצאות'!$D:$D,'כל ההוצאות'!$B:$B,"Manus AI",'כל ההוצאות'!$F:$F,"יולי 2025") | C19: =SUMIFS('כל ההוצאות'!$E:$E,'כל ההוצאות'!$B:$B,"Manus AI",'כל ההוצאות'!$F:$F,"יולי 2025") | D19: =SUMIFS('כל ההוצאות'!$D:$D,'כל ההוצאות'!$B:$B,"Manus AI",'כל ההוצאות'!$F:$F,"אוגוסט 2025") | E19: =SUMIFS('כל ההוצאות'!$E:$E,'כל ההוצאות'!$B:$B,"Manus AI",'כל ההוצאות'!$F:$F,"אוגוסט 2025") | F19: =SUMIFS('כל ההוצאות'!$D:$D,'כל ההוצאות'!$B:$B,"Manus AI",'כל ההוצאות'!$F:$F,"ספטמבר 2025") | G19: =SUMIFS('כל ההוצאות'!$E:$E,'כל ההוצאות'!$B:$B,"Manus AI",'כל ההוצאות'!$F:$F,"ספטמבר 2025") | H19: =SUMIFS('כל ההוצאות'!$D:$D,'כל ההוצאות'!$B:$B,"Manus AI",'כל ההוצאות'!$F:$F,"אוקטובר 2025") | I19: =SUMIFS('כל ההוצאות'!$E:$E,'כל ההוצאות'!$B:$B,"Manus AI",'כל ההוצאות'!$F:$F,"אוקטובר 2025") | J19: =SUMIFS('כל ההוצאות'!$D:$D,'כל ההוצאות'!$B:$B,"Manus AI",'כל ההוצאות'!$F:$F,"נובמבר 2025") | K19: =SUMIFS('כל ההוצאות'!$E:$E,'כל ההוצאות'!$B:$B,"Manus AI",'כל ההוצאות'!$F:$F,"נובמבר 2025") | L19: =SUMIFS('כל ההוצאות'!$D:$D,'כל ההוצאות'!$B:$B,"Manus AI",'כל ההוצאות'!$F:$F,"דצמבר 2025") | M19: =SUMIFS('כל ההוצאות'!$E:$E,'כל ההוצאות'!$B:$B,"Manus AI",'כל ההוצאות'!$F:$F,"דצמבר 2025") | N19: =SUMIFS('כל ההוצאות'!$D:$D,'כל ההוצאות'!$B:$B,"Manus AI",'כל ההוצאות'!$F:$F,"ינואר 2026") | O19: =SUMIFS('כל ההוצאות'!$E:$E,'כל ההוצאות'!$B:$B,"Manus AI",'כל ההוצאות'!$F:$F,"ינואר 2026") | P19: =SUMIFS('כל ההוצאות'!$D:$D,'כל ההוצאות'!$B:$B,"Manus AI",'כל ההוצאות'!$F:$F,"פברואר 2026") | Q19: =SUMIFS('כל ההוצאות'!$E:$E,'כל ההוצאות'!$B:$B,"Manus AI",'כל ההוצאות'!$F:$F,"פברואר 2026") | R19: =SUMIFS('כל ההוצאות'!$D:$D,'כל ההוצאות'!$B:$B,"Manus AI",'כל ההוצאות'!$F:$F,"מרץ 2026") | S19: =SUMIFS('כל ההוצאות'!$E:$E,'כל ההוצאות'!$B:$B,"Manus AI",'כל ההוצאות'!$F:$F,"מרץ 2026") | T19: =SUMIFS('כל ההוצאות'!$D:$D,'כל ההוצאות'!$B:$B,"Manus AI",'כל ההוצאות'!$F:$F,"אפריל 2026") | U19: =SUMIFS('כל ההוצאות'!$E:$E,'כל ההוצאות'!$B:$B,"Manus AI",'כל ההוצאות'!$F:$F,"אפריל 2026") | V19: =SUMIFS('כל ההוצאות'!$D:$D,'כל ההוצאות'!$B:$B,"Manus AI",'כל ההוצאות'!$F:$F,"מאי 2026") | W19: =SUMIFS('כל ההוצאות'!$E:$E,'כל ההוצאות'!$B:$B,"Manus AI",'כל ההוצאות'!$F:$F,"מאי 2026") | X19: =SUMIFS('כל ההוצאות'!$D:$D,'כל ההוצאות'!$B:$B,"Manus AI",'כל ההוצאות'!$F:$F,"יוני 2026") | Y19: =SUMIFS('כל ההוצאות'!$E:$E,'כל ההוצאות'!$B:$B,"Manus AI",'כל ההוצאות'!$F:$F,"יוני 2026") | Z19: =SUMIFS('כל ההוצאות'!$D:$D,'כל ההוצאות'!$B:$B,"Manus AI",'כל ההוצאות'!$F:$F,"יולי 2026") | AA19: =SUMIFS('כל ההוצאות'!$E:$E,'כל ההוצאות'!$B:$B,"Manus AI",'כל ההוצאות'!$F:$F,"יולי 2026") | AB19: =SUMIFS('כל ההוצאות'!$D:$D,'כל ההוצאות'!$B:$B,"Manus AI",'כל ההוצאות'!$F:$F,"אוגוסט 2026") | AC19: =SUMIFS('כל ההוצאות'!$E:$E,'כל ההוצאות'!$B:$B,"Manus AI",'כל ההוצאות'!$F:$F,"אוגוסט 2026") | AD19: =SUMIFS('כל ההוצאות'!$D:$D,'כל ההוצאות'!$B:$B,"Manus AI",'כל ההוצאות'!$F:$F,"ספטמבר 2026") | AE19: =SUMIFS('כל ההוצאות'!$E:$E,'כל ההוצאות'!$B:$B,"Manus AI",'כל ההוצאות'!$F:$F,"ספטמבר 2026") | AF19: =SUMIFS('כל ההוצאות'!$D:$D,'כל ההוצאות'!$B:$B,"Manus AI",'כל ההוצאות'!$F:$F,"אוקטובר 2026") | AG19: =SUMIFS('כל ההוצאות'!$E:$E,'כל ההוצאות'!$B:$B,"Manus AI",'כל ההוצאות'!$F:$F,"אוקטובר 2026") | AH19: =SUMIFS('כל ההוצאות'!$D:$D,'כל ההוצאות'!$B:$B,"Manus AI",'כל ההוצאות'!$F:$F,"נובמבר 2026") | AI19: =SUMIFS('כל ההוצאות'!$E:$E,'כל ההוצאות'!$B:$B,"Manus AI",'כל ההוצאות'!$F:$F,"נובמבר 2026") | AJ19: =SUMIFS('כל ההוצאות'!$D:$D,'כל ההוצאות'!$B:$B,"Manus AI",'כל ההוצאות'!$F:$F,"דצמבר 2026") | AK19: =SUMIFS('כל ההוצאות'!$E:$E,'כל ההוצאות'!$B:$B,"Manus AI",'כל ההוצאות'!$F:$F,"דצמבר 2026") | AL19: =SUM(B19,D19,F19,H19,J19,L19,N19,P19,R19,T19,V19,X19,Z19,AB19,AD19,AF19,AH19,AJ19) | AM19: =SUM(C19,E19,G19,I19,K19,M19,O19,Q19,S19,U19,W19,Y19,AA19,AC19,AE19,AG19,AI19,AK19)
A20: Manychat | B20: =SUMIFS('כל ההוצאות'!$D:$D,'כל ההוצאות'!$B:$B,"Manychat",'כל ההוצאות'!$F:$F,"יולי 2025") | C20: =SUMIFS('כל ההוצאות'!$E:$E,'כל ההוצאות'!$B:$B,"Manychat",'כל ההוצאות'!$F:$F,"יולי 2025") | D20: =SUMIFS('כל ההוצאות'!$D:$D,'כל ההוצאות'!$B:$B,"Manychat",'כל ההוצאות'!$F:$F,"אוגוסט 2025") | E20: =SUMIFS('כל ההוצאות'!$E:$E,'כל ההוצאות'!$B:$B,"Manychat",'כל ההוצאות'!$F:$F,"אוגוסט 2025") | F20: =SUMIFS('כל ההוצאות'!$D:$D,'כל ההוצאות'!$B:$B,"Manychat",'כל ההוצאות'!$F:$F,"ספטמבר 2025") | G20: =SUMIFS('כל ההוצאות'!$E:$E,'כל ההוצאות'!$B:$B,"Manychat",'כל ההוצאות'!$F:$F,"ספטמבר 2025") | H20: =SUMIFS('כל ההוצאות'!$D:$D,'כל ההוצאות'!$B:$B,"Manychat",'כל ההוצאות'!$F:$F,"אוקטובר 2025") | I20: =SUMIFS('כל ההוצאות'!$E:$E,'כל ההוצאות'!$B:$B,"Manychat",'כל ההוצאות'!$F:$F,"אוקטובר 2025") | J20: =SUMIFS('כל ההוצאות'!$D:$D,'כל ההוצאות'!$B:$B,"Manychat",'כל ההוצאות'!$F:$F,"נובמבר 2025") | K20: =SUMIFS('כל ההוצאות'!$E:$E,'כל ההוצאות'!$B:$B,"Manychat",'כל ההוצאות'!$F:$F,"נובמבר 2025") | L20: =SUMIFS('כל ההוצאות'!$D:$D,'כל ההוצאות'!$B:$B,"Manychat",'כל ההוצאות'!$F:$F,"דצמבר 2025") | M20: =SUMIFS('כל ההוצאות'!$E:$E,'כל ההוצאות'!$B:$B,"Manychat",'כל ההוצאות'!$F:$F,"דצמבר 2025") | N20: =SUMIFS('כל ההוצאות'!$D:$D,'כל ההוצאות'!$B:$B,"Manychat",'כל ההוצאות'!$F:$F,"ינואר 2026") | O20: =SUMIFS('כל ההוצאות'!$E:$E,'כל ההוצאות'!$B:$B,"Manychat",'כל ההוצאות'!$F:$F,"ינואר 2026") | P20: =SUMIFS('כל ההוצאות'!$D:$D,'כל ההוצאות'!$B:$B,"Manychat",'כל ההוצאות'!$F:$F,"פברואר 2026") | Q20: =SUMIFS('כל ההוצאות'!$E:$E,'כל ההוצאות'!$B:$B,"Manychat",'כל ההוצאות'!$F:$F,"פברואר 2026") | R20: =SUMIFS('כל ההוצאות'!$D:$D,'כל ההוצאות'!$B:$B,"Manychat",'כל ההוצאות'!$F:$F,"מרץ 2026") | S20: =SUMIFS('כל ההוצאות'!$E:$E,'כל ההוצאות'!$B:$B,"Manychat",'כל ההוצאות'!$F:$F,"מרץ 2026") | T20: =SUMIFS('כל ההוצאות'!$D:$D,'כל ההוצאות'!$B:$B,"Manychat",'כל ההוצאות'!$F:$F,"אפריל 2026") | U20: =SUMIFS('כל ההוצאות'!$E:$E,'כל ההוצאות'!$B:$B,"Manychat",'כל ההוצאות'!$F:$F,"אפריל 2026") | V20: =SUMIFS('כל ההוצאות'!$D:$D,'כל ההוצאות'!$B:$B,"Manychat",'כל ההוצאות'!$F:$F,"מאי 2026") | W20: =SUMIFS('כל ההוצאות'!$E:$E,'כל ההוצאות'!$B:$B,"Manychat",'כל ההוצאות'!$F:$F,"מאי 2026") | X20: =SUMIFS('כל ההוצאות'!$D:$D,'כל ההוצאות'!$B:$B,"Manychat",'כל ההוצאות'!$F:$F,"יוני 2026") | Y20: =SUMIFS('כל ההוצאות'!$E:$E,'כל ההוצאות'!$B:$B,"Manychat",'כל ההוצאות'!$F:$F,"יוני 2026") | Z20: =SUMIFS('כל ההוצאות'!$D:$D,'כל ההוצאות'!$B:$B,"Manychat",'כל ההוצאות'!$F:$F,"יולי 2026") | AA20: =SUMIFS('כל ההוצאות'!$E:$E,'כל ההוצאות'!$B:$B,"Manychat",'כל ההוצאות'!$F:$F,"יולי 2026") | AB20: =SUMIFS('כל ההוצאות'!$D:$D,'כל ההוצאות'!$B:$B,"Manychat",'כל ההוצאות'!$F:$F,"אוגוסט 2026") | AC20: =SUMIFS('כל ההוצאות'!$E:$E,'כל ההוצאות'!$B:$B,"Manychat",'כל ההוצאות'!$F:$F,"אוגוסט 2026") | AD20: =SUMIFS('כל ההוצאות'!$D:$D,'כל ההוצאות'!$B:$B,"Manychat",'כל ההוצאות'!$F:$F,"ספטמבר 2026") | AE20: =SUMIFS('כל ההוצאות'!$E:$E,'כל ההוצאות'!$B:$B,"Manychat",'כל ההוצאות'!$F:$F,"ספטמבר 2026") | AF20: =SUMIFS('כל ההוצאות'!$D:$D,'כל ההוצאות'!$B:$B,"Manychat",'כל ההוצאות'!$F:$F,"אוקטובר 2026") | AG20: =SUMIFS('כל ההוצאות'!$E:$E,'כל ההוצאות'!$B:$B,"Manychat",'כל ההוצאות'!$F:$F,"אוקטובר 2026") | AH20: =SUMIFS('כל ההוצאות'!$D:$D,'כל ההוצאות'!$B:$B,"Manychat",'כל ההוצאות'!$F:$F,"נובמבר 2026") | AI20: =SUMIFS('כל ההוצאות'!$E:$E,'כל ההוצאות'!$B:$B,"Manychat",'כל ההוצאות'!$F:$F,"נובמבר 2026") | AJ20: =SUMIFS('כל ההוצאות'!$D:$D,'כל ההוצאות'!$B:$B,"Manychat",'כל ההוצאות'!$F:$F,"דצמבר 2026") | AK20: =SUMIFS('כל ההוצאות'!$E:$E,'כל ההוצאות'!$B:$B,"Manychat",'כל ההוצאות'!$F:$F,"דצמבר 2026") | AL20: =SUM(B20,D20,F20,H20,J20,L20,N20,P20,R20,T20,V20,X20,Z20,AB20,AD20,AF20,AH20,AJ20) | AM20: =SUM(C20,E20,G20,I20,K20,M20,O20,Q20,S20,U20,W20,Y20,AA20,AC20,AE20,AG20,AI20,AK20)
A21: Meta (Ads) | B21: =SUMIFS('כל ההוצאות'!$D:$D,'כל ההוצאות'!$B:$B,"Meta (Ads)",'כל ההוצאות'!$F:$F,"יולי 2025") | C21: =SUMIFS('כל ההוצאות'!$E:$E,'כל ההוצאות'!$B:$B,"Meta (Ads)",'כל ההוצאות'!$F:$F,"יולי 2025") | D21: =SUMIFS('כל ההוצאות'!$D:$D,'כל ההוצאות'!$B:$B,"Meta (Ads)",'כל ההוצאות'!$F:$F,"אוגוסט 2025") | E21: =SUMIFS('כל ההוצאות'!$E:$E,'כל ההוצאות'!$B:$B,"Meta (Ads)",'כל ההוצאות'!$F:$F,"אוגוסט 2025") | F21: =SUMIFS('כל ההוצאות'!$D:$D,'כל ההוצאות'!$B:$B,"Meta (Ads)",'כל ההוצאות'!$F:$F,"ספטמבר 2025") | G21: =SUMIFS('כל ההוצאות'!$E:$E,'כל ההוצאות'!$B:$B,"Meta (Ads)",'כל ההוצאות'!$F:$F,"ספטמבר 2025") | H21: =SUMIFS('כל ההוצאות'!$D:$D,'כל ההוצאות'!$B:$B,"Meta (Ads)",'כל ההוצאות'!$F:$F,"אוקטובר 2025") | I21: =SUMIFS('כל ההוצאות'!$E:$E,'כל ההוצאות'!$B:$B,"Meta (Ads)",'כל ההוצאות'!$F:$F,"אוקטובר 2025") | J21: =SUMIFS('כל ההוצאות'!$D:$D,'כל ההוצאות'!$B:$B,"Meta (Ads)",'כל ההוצאות'!$F:$F,"נובמבר 2025") | K21: =SUMIFS('כל ההוצאות'!$E:$E,'כל ההוצאות'!$B:$B,"Meta (Ads)",'כל ההוצאות'!$F:$F,"נובמבר 2025") | L21: =SUMIFS('כל ההוצאות'!$D:$D,'כל ההוצאות'!$B:$B,"Meta (Ads)",'כל ההוצאות'!$F:$F,"דצמבר 2025") | M21: =SUMIFS('כל ההוצאות'!$E:$E,'כל ההוצאות'!$B:$B,"Meta (Ads)",'כל ההוצאות'!$F:$F,"דצמבר 2025") | N21: =SUMIFS('כל ההוצאות'!$D:$D,'כל ההוצאות'!$B:$B,"Meta (Ads)",'כל ההוצאות'!$F:$F,"ינואר 2026") | O21: =SUMIFS('כל ההוצאות'!$E:$E,'כל ההוצאות'!$B:$B,"Meta (Ads)",'כל ההוצאות'!$F:$F,"ינואר 2026") | P21: =SUMIFS('כל ההוצאות'!$D:$D,'כל ההוצאות'!$B:$B,"Meta (Ads)",'כל ההוצאות'!$F:$F,"פברואר 2026") | Q21: =SUMIFS('כל ההוצאות'!$E:$E,'כל ההוצאות'!$B:$B,"Meta (Ads)",'כל ההוצאות'!$F:$F,"פברואר 2026") | R21: =SUMIFS('כל ההוצאות'!$D:$D,'כל ההוצאות'!$B:$B,"Meta (Ads)",'כל ההוצאות'!$F:$F,"מרץ 2026") | S21: =SUMIFS('כל ההוצאות'!$E:$E,'כל ההוצאות'!$B:$B,"Meta (Ads)",'כל ההוצאות'!$F:$F,"מרץ 2026") | T21: =SUMIFS('כל ההוצאות'!$D:$D,'כל ההוצאות'!$B:$B,"Meta (Ads)",'כל ההוצאות'!$F:$F,"אפריל 2026") | U21: =SUMIFS('כל ההוצאות'!$E:$E,'כל ההוצאות'!$B:$B,"Meta (Ads)",'כל ההוצאות'!$F:$F,"אפריל 2026") | V21: =SUMIFS('כל ההוצאות'!$D:$D,'כל ההוצאות'!$B:$B,"Meta (Ads)",'כל ההוצאות'!$F:$F,"מאי 2026") | W21: =SUMIFS('כל ההוצאות'!$E:$E,'כל ההוצאות'!$B:$B,"Meta (Ads)",'כל ההוצאות'!$F:$F,"מאי 2026") | X21: =SUMIFS('כל ההוצאות'!$D:$D,'כל ההוצאות'!$B:$B,"Meta (Ads)",'כל ההוצאות'!$F:$F,"יוני 2026") | Y21: =SUMIFS('כל ההוצאות'!$E:$E,'כל ההוצאות'!$B:$B,"Meta (Ads)",'כל ההוצאות'!$F:$F,"יוני 2026") | Z21: =SUMIFS('כל ההוצאות'!$D:$D,'כל ההוצאות'!$B:$B,"Meta (Ads)",'כל ההוצאות'!$F:$F,"יולי 2026") | AA21: =SUMIFS('כל ההוצאות'!$E:$E,'כל ההוצאות'!$B:$B,"Meta (Ads)",'כל ההוצאות'!$F:$F,"יולי 2026") | AB21: =SUMIFS('כל ההוצאות'!$D:$D,'כל ההוצאות'!$B:$B,"Meta (Ads)",'כל ההוצאות'!$F:$F,"אוגוסט 2026") | AC21: =SUMIFS('כל ההוצאות'!$E:$E,'כל ההוצאות'!$B:$B,"Meta (Ads)",'כל ההוצאות'!$F:$F,"אוגוסט 2026") | AD21: =SUMIFS('כל ההוצאות'!$D:$D,'כל ההוצאות'!$B:$B,"Meta (Ads)",'כל ההוצאות'!$F:$F,"ספטמבר 2026") | AE21: =SUMIFS('כל ההוצאות'!$E:$E,'כל ההוצאות'!$B:$B,"Meta (Ads)",'כל ההוצאות'!$F:$F,"ספטמבר 2026") | AF21: =SUMIFS('כל ההוצאות'!$D:$D,'כל ההוצאות'!$B:$B,"Meta (Ads)",'כל ההוצאות'!$F:$F,"אוקטובר 2026") | AG21: =SUMIFS('כל ההוצאות'!$E:$E,'כל ההוצאות'!$B:$B,"Meta (Ads)",'כל ההוצאות'!$F:$F,"אוקטובר 2026") | AH21: =SUMIFS('כל ההוצאות'!$D:$D,'כל ההוצאות'!$B:$B,"Meta (Ads)",'כל ההוצאות'!$F:$F,"נובמבר 2026") | AI21: =SUMIFS('כל ההוצאות'!$E:$E,'כל ההוצאות'!$B:$B,"Meta (Ads)",'כל ההוצאות'!$F:$F,"נובמבר 2026") | AJ21: =SUMIFS('כל ההוצאות'!$D:$D,'כל ההוצאות'!$B:$B,"Meta (Ads)",'כל ההוצאות'!$F:$F,"דצמבר 2026") | AK21: =SUMIFS('כל ההוצאות'!$E:$E,'כל ההוצאות'!$B:$B,"Meta (Ads)",'כל ההוצאות'!$F:$F,"דצמבר 2026") | AL21: =SUM(B21,D21,F21,H21,J21,L21,N21,P21,R21,T21,V21,X21,Z21,AB21,AD21,AF21,AH21,AJ21) | AM21: =SUM(C21,E21,G21,I21,K21,M21,O21,Q21,S21,U21,W21,Y21,AA21,AC21,AE21,AG21,AI21,AK21)
A22: OpenAI | B22: =SUMIFS('כל ההוצאות'!$D:$D,'כל ההוצאות'!$B:$B,"OpenAI",'כל ההוצאות'!$F:$F,"יולי 2025") | C22: =SUMIFS('כל ההוצאות'!$E:$E,'כל ההוצאות'!$B:$B,"OpenAI",'כל ההוצאות'!$F:$F,"יולי 2025") | D22: =SUMIFS('כל ההוצאות'!$D:$D,'כל ההוצאות'!$B:$B,"OpenAI",'כל ההוצאות'!$F:$F,"אוגוסט 2025") | E22: =SUMIFS('כל ההוצאות'!$E:$E,'כל ההוצאות'!$B:$B,"OpenAI",'כל ההוצאות'!$F:$F,"אוגוסט 2025") | F22: =SUMIFS('כל ההוצאות'!$D:$D,'כל ההוצאות'!$B:$B,"OpenAI",'כל ההוצאות'!$F:$F,"ספטמבר 2025") | G22: =SUMIFS('כל ההוצאות'!$E:$E,'כל ההוצאות'!$B:$B,"OpenAI",'כל ההוצאות'!$F:$F,"ספטמבר 2025") | H22: =SUMIFS('כל ההוצאות'!$D:$D,'כל ההוצאות'!$B:$B,"OpenAI",'כל ההוצאות'!$F:$F,"אוקטובר 2025") | I22: =SUMIFS('כל ההוצאות'!$E:$E,'כל ההוצאות'!$B:$B,"OpenAI",'כל ההוצאות'!$F:$F,"אוקטובר 2025") | J22: =SUMIFS('כל ההוצאות'!$D:$D,'כל ההוצאות'!$B:$B,"OpenAI",'כל ההוצאות'!$F:$F,"נובמבר 2025") | K22: =SUMIFS('כל ההוצאות'!$E:$E,'כל ההוצאות'!$B:$B,"OpenAI",'כל ההוצאות'!$F:$F,"נובמבר 2025") | L22: =SUMIFS('כל ההוצאות'!$D:$D,'כל ההוצאות'!$B:$B,"OpenAI",'כל ההוצאות'!$F:$F,"דצמבר 2025") | M22: =SUMIFS('כל ההוצאות'!$E:$E,'כל ההוצאות'!$B:$B,"OpenAI",'כל ההוצאות'!$F:$F,"דצמבר 2025") | N22: =SUMIFS('כל ההוצאות'!$D:$D,'כל ההוצאות'!$B:$B,"OpenAI",'כל ההוצאות'!$F:$F,"ינואר 2026") | O22: =SUMIFS('כל ההוצאות'!$E:$E,'כל ההוצאות'!$B:$B,"OpenAI",'כל ההוצאות'!$F:$F,"ינואר 2026") | P22: =SUMIFS('כל ההוצאות'!$D:$D,'כל ההוצאות'!$B:$B,"OpenAI",'כל ההוצאות'!$F:$F,"פברואר 2026") | Q22: =SUMIFS('כל ההוצאות'!$E:$E,'כל ההוצאות'!$B:$B,"OpenAI",'כל ההוצאות'!$F:$F,"פברואר 2026") | R22: =SUMIFS('כל ההוצאות'!$D:$D,'כל ההוצאות'!$B:$B,"OpenAI",'כל ההוצאות'!$F:$F,"מרץ 2026") | S22: =SUMIFS('כל ההוצאות'!$E:$E,'כל ההוצאות'!$B:$B,"OpenAI",'כל ההוצאות'!$F:$F,"מרץ 2026") | T22: =SUMIFS('כל ההוצאות'!$D:$D,'כל ההוצאות'!$B:$B,"OpenAI",'כל ההוצאות'!$F:$F,"אפריל 2026") | U22: =SUMIFS('כל ההוצאות'!$E:$E,'כל ההוצאות'!$B:$B,"OpenAI",'כל ההוצאות'!$F:$F,"אפריל 2026") | V22: =SUMIFS('כל ההוצאות'!$D:$D,'כל ההוצאות'!$B:$B,"OpenAI",'כל ההוצאות'!$F:$F,"מאי 2026") | W22: =SUMIFS('כל ההוצאות'!$E:$E,'כל ההוצאות'!$B:$B,"OpenAI",'כל ההוצאות'!$F:$F,"מאי 2026") | X22: =SUMIFS('כל ההוצאות'!$D:$D,'כל ההוצאות'!$B:$B,"OpenAI",'כל ההוצאות'!$F:$F,"יוני 2026") | Y22: =SUMIFS('כל ההוצאות'!$E:$E,'כל ההוצאות'!$B:$B,"OpenAI",'כל ההוצאות'!$F:$F,"יוני 2026") | Z22: =SUMIFS('כל ההוצאות'!$D:$D,'כל ההוצאות'!$B:$B,"OpenAI",'כל ההוצאות'!$F:$F,"יולי 2026") | AA22: =SUMIFS('כל ההוצאות'!$E:$E,'כל ההוצאות'!$B:$B,"OpenAI",'כל ההוצאות'!$F:$F,"יולי 2026") | AB22: =SUMIFS('כל ההוצאות'!$D:$D,'כל ההוצאות'!$B:$B,"OpenAI",'כל ההוצאות'!$F:$F,"אוגוסט 2026") | AC22: =SUMIFS('כל ההוצאות'!$E:$E,'כל ההוצאות'!$B:$B,"OpenAI",'כל ההוצאות'!$F:$F,"אוגוסט 2026") | AD22: =SUMIFS('כל ההוצאות'!$D:$D,'כל ההוצאות'!$B:$B,"OpenAI",'כל ההוצאות'!$F:$F,"ספטמבר 2026") | AE22: =SUMIFS('כל ההוצאות'!$E:$E,'כל ההוצאות'!$B:$B,"OpenAI",'כל ההוצאות'!$F:$F,"ספטמבר 2026") | AF22: =SUMIFS('כל ההוצאות'!$D:$D,'כל ההוצאות'!$B:$B,"OpenAI",'כל ההוצאות'!$F:$F,"אוקטובר 2026") | AG22: =SUMIFS('כל ההוצאות'!$E:$E,'כל ההוצאות'!$B:$B,"OpenAI",'כל ההוצאות'!$F:$F,"אוקטובר 2026") | AH22: =SUMIFS('כל ההוצאות'!$D:$D,'כל ההוצאות'!$B:$B,"OpenAI",'כל ההוצאות'!$F:$F,"נובמבר 2026") | AI22: =SUMIFS('כל ההוצאות'!$E:$E,'כל ההוצאות'!$B:$B,"OpenAI",'כל ההוצאות'!$F:$F,"נובמבר 2026") | AJ22: =SUMIFS('כל ההוצאות'!$D:$D,'כל ההוצאות'!$B:$B,"OpenAI",'כל ההוצאות'!$F:$F,"דצמבר 2026") | AK22: =SUMIFS('כל ההוצאות'!$E:$E,'כל ההוצאות'!$B:$B,"OpenAI",'כל ההוצאות'!$F:$F,"דצמבר 2026") | AL22: =SUM(B22,D22,F22,H22,J22,L22,N22,P22,R22,T22,V22,X22,Z22,AB22,AD22,AF22,AH22,AJ22) | AM22: =SUM(C22,E22,G22,I22,K22,M22,O22,Q22,S22,U22,W22,Y22,AA22,AC22,AE22,AG22,AI22,AK22)
A23: Recraft | B23: =SUMIFS('כל ההוצאות'!$D:$D,'כל ההוצאות'!$B:$B,"Recraft",'כל ההוצאות'!$F:$F,"יולי 2025") | C23: =SUMIFS('כל ההוצאות'!$E:$E,'כל ההוצאות'!$B:$B,"Recraft",'כל ההוצאות'!$F:$F,"יולי 2025") | D23: =SUMIFS('כל ההוצאות'!$D:$D,'כל ההוצאות'!$B:$B,"Recraft",'כל ההוצאות'!$F:$F,"אוגוסט 2025") | E23: =SUMIFS('כל ההוצאות'!$E:$E,'כל ההוצאות'!$B:$B,"Recraft",'כל ההוצאות'!$F:$F,"אוגוסט 2025") | F23: =SUMIFS('כל ההוצאות'!$D:$D,'כל ההוצאות'!$B:$B,"Recraft",'כל ההוצאות'!$F:$F,"ספטמבר 2025") | G23: =SUMIFS('כל ההוצאות'!$E:$E,'כל ההוצאות'!$B:$B,"Recraft",'כל ההוצאות'!$F:$F,"ספטמבר 2025") | H23: =SUMIFS('כל ההוצאות'!$D:$D,'כל ההוצאות'!$B:$B,"Recraft",'כל ההוצאות'!$F:$F,"אוקטובר 2025") | I23: =SUMIFS('כל ההוצאות'!$E:$E,'כל ההוצאות'!$B:$B,"Recraft",'כל ההוצאות'!$F:$F,"אוקטובר 2025") | J23: =SUMIFS('כל ההוצאות'!$D:$D,'כל ההוצאות'!$B:$B,"Recraft",'כל ההוצאות'!$F:$F,"נובמבר 2025") | K23: =SUMIFS('כל ההוצאות'!$E:$E,'כל ההוצאות'!$B:$B,"Recraft",'כל ההוצאות'!$F:$F,"נובמבר 2025") | L23: =SUMIFS('כל ההוצאות'!$D:$D,'כל ההוצאות'!$B:$B,"Recraft",'כל ההוצאות'!$F:$F,"דצמבר 2025") | M23: =SUMIFS('כל ההוצאות'!$E:$E,'כל ההוצאות'!$B:$B,"Recraft",'כל ההוצאות'!$F:$F,"דצמבר 2025") | N23: =SUMIFS('כל ההוצאות'!$D:$D,'כל ההוצאות'!$B:$B,"Recraft",'כל ההוצאות'!$F:$F,"ינואר 2026") | O23: =SUMIFS('כל ההוצאות'!$E:$E,'כל ההוצאות'!$B:$B,"Recraft",'כל ההוצאות'!$F:$F,"ינואר 2026") | P23: =SUMIFS('כל ההוצאות'!$D:$D,'כל ההוצאות'!$B:$B,"Recraft",'כל ההוצאות'!$F:$F,"פברואר 2026") | Q23: =SUMIFS('כל ההוצאות'!$E:$E,'כל ההוצאות'!$B:$B,"Recraft",'כל ההוצאות'!$F:$F,"פברואר 2026") | R23: =SUMIFS('כל ההוצאות'!$D:$D,'כל ההוצאות'!$B:$B,"Recraft",'כל ההוצאות'!$F:$F,"מרץ 2026") | S23: =SUMIFS('כל ההוצאות'!$E:$E,'כל ההוצאות'!$B:$B,"Recraft",'כל ההוצאות'!$F:$F,"מרץ 2026") | T23: =SUMIFS('כל ההוצאות'!$D:$D,'כל ההוצאות'!$B:$B,"Recraft",'כל ההוצאות'!$F:$F,"אפריל 2026") | U23: =SUMIFS('כל ההוצאות'!$E:$E,'כל ההוצאות'!$B:$B,"Recraft",'כל ההוצאות'!$F:$F,"אפריל 2026") | V23: =SUMIFS('כל ההוצאות'!$D:$D,'כל ההוצאות'!$B:$B,"Recraft",'כל ההוצאות'!$F:$F,"מאי 2026") | W23: =SUMIFS('כל ההוצאות'!$E:$E,'כל ההוצאות'!$B:$B,"Recraft",'כל ההוצאות'!$F:$F,"מאי 2026") | X23: =SUMIFS('כל ההוצאות'!$D:$D,'כל ההוצאות'!$B:$B,"Recraft",'כל ההוצאות'!$F:$F,"יוני 2026") | Y23: =SUMIFS('כל ההוצאות'!$E:$E,'כל ההוצאות'!$B:$B,"Recraft",'כל ההוצאות'!$F:$F,"יוני 2026") | Z23: =SUMIFS('כל ההוצאות'!$D:$D,'כל ההוצאות'!$B:$B,"Recraft",'כל ההוצאות'!$F:$F,"יולי 2026") | AA23: =SUMIFS('כל ההוצאות'!$E:$E,'כל ההוצאות'!$B:$B,"Recraft",'כל ההוצאות'!$F:$F,"יולי 2026") | AB23: =SUMIFS('כל ההוצאות'!$D:$D,'כל ההוצאות'!$B:$B,"Recraft",'כל ההוצאות'!$F:$F,"אוגוסט 2026") | AC23: =SUMIFS('כל ההוצאות'!$E:$E,'כל ההוצאות'!$B:$B,"Recraft",'כל ההוצאות'!$F:$F,"אוגוסט 2026") | AD23: =SUMIFS('כל ההוצאות'!$D:$D,'כל ההוצאות'!$B:$B,"Recraft",'כל ההוצאות'!$F:$F,"ספטמבר 2026") | AE23: =SUMIFS('כל ההוצאות'!$E:$E,'כל ההוצאות'!$B:$B,"Recraft",'כל ההוצאות'!$F:$F,"ספטמבר 2026") | AF23: =SUMIFS('כל ההוצאות'!$D:$D,'כל ההוצאות'!$B:$B,"Recraft",'כל ההוצאות'!$F:$F,"אוקטובר 2026") | AG23: =SUMIFS('כל ההוצאות'!$E:$E,'כל ההוצאות'!$B:$B,"Recraft",'כל ההוצאות'!$F:$F,"אוקטובר 2026") | AH23: =SUMIFS('כל ההוצאות'!$D:$D,'כל ההוצאות'!$B:$B,"Recraft",'כל ההוצאות'!$F:$F,"נובמבר 2026") | AI23: =SUMIFS('כל ההוצאות'!$E:$E,'כל ההוצאות'!$B:$B,"Recraft",'כל ההוצאות'!$F:$F,"נובמבר 2026") | AJ23: =SUMIFS('כל ההוצאות'!$D:$D,'כל ההוצאות'!$B:$B,"Recraft",'כל ההוצאות'!$F:$F,"דצמבר 2026") | AK23: =SUMIFS('כל ההוצאות'!$E:$E,'כל ההוצאות'!$B:$B,"Recraft",'כל ההוצאות'!$F:$F,"דצמבר 2026") | AL23: =SUM(B23,D23,F23,H23,J23,L23,N23,P23,R23,T23,V23,X23,Z23,AB23,AD23,AF23,AH23,AJ23) | AM23: =SUM(C23,E23,G23,I23,K23,M23,O23,Q23,S23,U23,W23,Y23,AA23,AC23,AE23,AG23,AI23,AK23)
A24: Replicate | B24: =SUMIFS('כל ההוצאות'!$D:$D,'כל ההוצאות'!$B:$B,"Replicate",'כל ההוצאות'!$F:$F,"יולי 2025") | C24: =SUMIFS('כל ההוצאות'!$E:$E,'כל ההוצאות'!$B:$B,"Replicate",'כל ההוצאות'!$F:$F,"יולי 2025") | D24: =SUMIFS('כל ההוצאות'!$D:$D,'כל ההוצאות'!$B:$B,"Replicate",'כל ההוצאות'!$F:$F,"אוגוסט 2025") | E24: =SUMIFS('כל ההוצאות'!$E:$E,'כל ההוצאות'!$B:$B,"Replicate",'כל ההוצאות'!$F:$F,"אוגוסט 2025") | F24: =SUMIFS('כל ההוצאות'!$D:$D,'כל ההוצאות'!$B:$B,"Replicate",'כל ההוצאות'!$F:$F,"ספטמבר 2025") | G24: =SUMIFS('כל ההוצאות'!$E:$E,'כל ההוצאות'!$B:$B,"Replicate",'כל ההוצאות'!$F:$F,"ספטמבר 2025") | H24: =SUMIFS('כל ההוצאות'!$D:$D,'כל ההוצאות'!$B:$B,"Replicate",'כל ההוצאות'!$F:$F,"אוקטובר 2025") | I24: =SUMIFS('כל ההוצאות'!$E:$E,'כל ההוצאות'!$B:$B,"Replicate",'כל ההוצאות'!$F:$F,"אוקטובר 2025") | J24: =SUMIFS('כל ההוצאות'!$D:$D,'כל ההוצאות'!$B:$B,"Replicate",'כל ההוצאות'!$F:$F,"נובמבר 2025") | K24: =SUMIFS('כל ההוצאות'!$E:$E,'כל ההוצאות'!$B:$B,"Replicate",'כל ההוצאות'!$F:$F,"נובמבר 2025") | L24: =SUMIFS('כל ההוצאות'!$D:$D,'כל ההוצאות'!$B:$B,"Replicate",'כל ההוצאות'!$F:$F,"דצמבר 2025") | M24: =SUMIFS('כל ההוצאות'!$E:$E,'כל ההוצאות'!$B:$B,"Replicate",'כל ההוצאות'!$F:$F,"דצמבר 2025") | N24: =SUMIFS('כל ההוצאות'!$D:$D,'כל ההוצאות'!$B:$B,"Replicate",'כל ההוצאות'!$F:$F,"ינואר 2026") | O24: =SUMIFS('כל ההוצאות'!$E:$E,'כל ההוצאות'!$B:$B,"Replicate",'כל ההוצאות'!$F:$F,"ינואר 2026") | P24: =SUMIFS('כל ההוצאות'!$D:$D,'כל ההוצאות'!$B:$B,"Replicate",'כל ההוצאות'!$F:$F,"פברואר 2026") | Q24: =SUMIFS('כל ההוצאות'!$E:$E,'כל ההוצאות'!$B:$B,"Replicate",'כל ההוצאות'!$F:$F,"פברואר 2026") | R24: =SUMIFS('כל ההוצאות'!$D:$D,'כל ההוצאות'!$B:$B,"Replicate",'כל ההוצאות'!$F:$F,"מרץ 2026") | S24: =SUMIFS('כל ההוצאות'!$E:$E,'כל ההוצאות'!$B:$B,"Replicate",'כל ההוצאות'!$F:$F,"מרץ 2026") | T24: =SUMIFS('כל ההוצאות'!$D:$D,'כל ההוצאות'!$B:$B,"Replicate",'כל ההוצאות'!$F:$F,"אפריל 2026") | U24: =SUMIFS('כל ההוצאות'!$E:$E,'כל ההוצאות'!$B:$B,"Replicate",'כל ההוצאות'!$F:$F,"אפריל 2026") | V24: =SUMIFS('כל ההוצאות'!$D:$D,'כל ההוצאות'!$B:$B,"Replicate",'כל ההוצאות'!$F:$F,"מאי 2026") | W24: =SUMIFS('כל ההוצאות'!$E:$E,'כל ההוצאות'!$B:$B,"Replicate",'כל ההוצאות'!$F:$F,"מאי 2026") | X24: =SUMIFS('כל ההוצאות'!$D:$D,'כל ההוצאות'!$B:$B,"Replicate",'כל ההוצאות'!$F:$F,"יוני 2026") | Y24: =SUMIFS('כל ההוצאות'!$E:$E,'כל ההוצאות'!$B:$B,"Replicate",'כל ההוצאות'!$F:$F,"יוני 2026") | Z24: =SUMIFS('כל ההוצאות'!$D:$D,'כל ההוצאות'!$B:$B,"Replicate",'כל ההוצאות'!$F:$F,"יולי 2026") | AA24: =SUMIFS('כל ההוצאות'!$E:$E,'כל ההוצאות'!$B:$B,"Replicate",'כל ההוצאות'!$F:$F,"יולי 2026") | AB24: =SUMIFS('כל ההוצאות'!$D:$D,'כל ההוצאות'!$B:$B,"Replicate",'כל ההוצאות'!$F:$F,"אוגוסט 2026") | AC24: =SUMIFS('כל ההוצאות'!$E:$E,'כל ההוצאות'!$B:$B,"Replicate",'כל ההוצאות'!$F:$F,"אוגוסט 2026") | AD24: =SUMIFS('כל ההוצאות'!$D:$D,'כל ההוצאות'!$B:$B,"Replicate",'כל ההוצאות'!$F:$F,"ספטמבר 2026") | AE24: =SUMIFS('כל ההוצאות'!$E:$E,'כל ההוצאות'!$B:$B,"Replicate",'כל ההוצאות'!$F:$F,"ספטמבר 2026") | AF24: =SUMIFS('כל ההוצאות'!$D:$D,'כל ההוצאות'!$B:$B,"Replicate",'כל ההוצאות'!$F:$F,"אוקטובר 2026") | AG24: =SUMIFS('כל ההוצאות'!$E:$E,'כל ההוצאות'!$B:$B,"Replicate",'כל ההוצאות'!$F:$F,"אוקטובר 2026") | AH24: =SUMIFS('כל ההוצאות'!$D:$D,'כל ההוצאות'!$B:$B,"Replicate",'כל ההוצאות'!$F:$F,"נובמבר 2026") | AI24: =SUMIFS('כל ההוצאות'!$E:$E,'כל ההוצאות'!$B:$B,"Replicate",'כל ההוצאות'!$F:$F,"נובמבר 2026") | AJ24: =SUMIFS('כל ההוצאות'!$D:$D,'כל ההוצאות'!$B:$B,"Replicate",'כל ההוצאות'!$F:$F,"דצמבר 2026") | AK24: =SUMIFS('כל ההוצאות'!$E:$E,'כל ההוצאות'!$B:$B,"Replicate",'כל ההוצאות'!$F:$F,"דצמבר 2026") | AL24: =SUM(B24,D24,F24,H24,J24,L24,N24,P24,R24,T24,V24,X24,Z24,AB24,AD24,AF24,AH24,AJ24) | AM24: =SUM(C24,E24,G24,I24,K24,M24,O24,Q24,S24,U24,W24,Y24,AA24,AC24,AE24,AG24,AI24,AK24)
A25: Runway ML | B25: =SUMIFS('כל ההוצאות'!$D:$D,'כל ההוצאות'!$B:$B,"Runway ML",'כל ההוצאות'!$F:$F,"יולי 2025") | C25: =SUMIFS('כל ההוצאות'!$E:$E,'כל ההוצאות'!$B:$B,"Runway ML",'כל ההוצאות'!$F:$F,"יולי 2025") | D25: =SUMIFS('כל ההוצאות'!$D:$D,'כל ההוצאות'!$B:$B,"Runway ML",'כל ההוצאות'!$F:$F,"אוגוסט 2025") | E25: =SUMIFS('כל ההוצאות'!$E:$E,'כל ההוצאות'!$B:$B,"Runway ML",'כל ההוצאות'!$F:$F,"אוגוסט 2025") | F25: =SUMIFS('כל ההוצאות'!$D:$D,'כל ההוצאות'!$B:$B,"Runway ML",'כל ההוצאות'!$F:$F,"ספטמבר 2025") | G25: =SUMIFS('כל ההוצאות'!$E:$E,'כל ההוצאות'!$B:$B,"Runway ML",'כל ההוצאות'!$F:$F,"ספטמבר 2025") | H25: =SUMIFS('כל ההוצאות'!$D:$D,'כל ההוצאות'!$B:$B,"Runway ML",'כל ההוצאות'!$F:$F,"אוקטובר 2025") | I25: =SUMIFS('כל ההוצאות'!$E:$E,'כל ההוצאות'!$B:$B,"Runway ML",'כל ההוצאות'!$F:$F,"אוקטובר 2025") | J25: =SUMIFS('כל ההוצאות'!$D:$D,'כל ההוצאות'!$B:$B,"Runway ML",'כל ההוצאות'!$F:$F,"נובמבר 2025") | K25: =SUMIFS('כל ההוצאות'!$E:$E,'כל ההוצאות'!$B:$B,"Runway ML",'כל ההוצאות'!$F:$F,"נובמבר 2025") | L25: =SUMIFS('כל ההוצאות'!$D:$D,'כל ההוצאות'!$B:$B,"Runway ML",'כל ההוצאות'!$F:$F,"דצמבר 2025") | M25: =SUMIFS('כל ההוצאות'!$E:$E,'כל ההוצאות'!$B:$B,"Runway ML",'כל ההוצאות'!$F:$F,"דצמבר 2025") | N25: =SUMIFS('כל ההוצאות'!$D:$D,'כל ההוצאות'!$B:$B,"Runway ML",'כל ההוצאות'!$F:$F,"ינואר 2026") | O25: =SUMIFS('כל ההוצאות'!$E:$E,'כל ההוצאות'!$B:$B,"Runway ML",'כל ההוצאות'!$F:$F,"ינואר 2026") | P25: =SUMIFS('כל ההוצאות'!$D:$D,'כל ההוצאות'!$B:$B,"Runway ML",'כל ההוצאות'!$F:$F,"פברואר 2026") | Q25: =SUMIFS('כל ההוצאות'!$E:$E,'כל ההוצאות'!$B:$B,"Runway ML",'כל ההוצאות'!$F:$F,"פברואר 2026") | R25: =SUMIFS('כל ההוצאות'!$D:$D,'כל ההוצאות'!$B:$B,"Runway ML",'כל ההוצאות'!$F:$F,"מרץ 2026") | S25: =SUMIFS('כל ההוצאות'!$E:$E,'כל ההוצאות'!$B:$B,"Runway ML",'כל ההוצאות'!$F:$F,"מרץ 2026") | T25: =SUMIFS('כל ההוצאות'!$D:$D,'כל ההוצאות'!$B:$B,"Runway ML",'כל ההוצאות'!$F:$F,"אפריל 2026") | U25: =SUMIFS('כל ההוצאות'!$E:$E,'כל ההוצאות'!$B:$B,"Runway ML",'כל ההוצאות'!$F:$F,"אפריל 2026") | V25: =SUMIFS('כל ההוצאות'!$D:$D,'כל ההוצאות'!$B:$B,"Runway ML",'כל ההוצאות'!$F:$F,"מאי 2026") | W25: =SUMIFS('כל ההוצאות'!$E:$E,'כל ההוצאות'!$B:$B,"Runway ML",'כל ההוצאות'!$F:$F,"מאי 2026") | X25: =SUMIFS('כל ההוצאות'!$D:$D,'כל ההוצאות'!$B:$B,"Runway ML",'כל ההוצאות'!$F:$F,"יוני 2026") | Y25: =SUMIFS('כל ההוצאות'!$E:$E,'כל ההוצאות'!$B:$B,"Runway ML",'כל ההוצאות'!$F:$F,"יוני 2026") | Z25: =SUMIFS('כל ההוצאות'!$D:$D,'כל ההוצאות'!$B:$B,"Runway ML",'כל ההוצאות'!$F:$F,"יולי 2026") | AA25: =SUMIFS('כל ההוצאות'!$E:$E,'כל ההוצאות'!$B:$B,"Runway ML",'כל ההוצאות'!$F:$F,"יולי 2026") | AB25: =SUMIFS('כל ההוצאות'!$D:$D,'כל ההוצאות'!$B:$B,"Runway ML",'כל ההוצאות'!$F:$F,"אוגוסט 2026") | AC25: =SUMIFS('כל ההוצאות'!$E:$E,'כל ההוצאות'!$B:$B,"Runway ML",'כל ההוצאות'!$F:$F,"אוגוסט 2026") | AD25: =SUMIFS('כל ההוצאות'!$D:$D,'כל ההוצאות'!$B:$B,"Runway ML",'כל ההוצאות'!$F:$F,"ספטמבר 2026") | AE25: =SUMIFS('כל ההוצאות'!$E:$E,'כל ההוצאות'!$B:$B,"Runway ML",'כל ההוצאות'!$F:$F,"ספטמבר 2026") | AF25: =SUMIFS('כל ההוצאות'!$D:$D,'כל ההוצאות'!$B:$B,"Runway ML",'כל ההוצאות'!$F:$F,"אוקטובר 2026") | AG25: =SUMIFS('כל ההוצאות'!$E:$E,'כל ההוצאות'!$B:$B,"Runway ML",'כל ההוצאות'!$F:$F,"אוקטובר 2026") | AH25: =SUMIFS('כל ההוצאות'!$D:$D,'כל ההוצאות'!$B:$B,"Runway ML",'כל ההוצאות'!$F:$F,"נובמבר 2026") | AI25: =SUMIFS('כל ההוצאות'!$E:$E,'כל ההוצאות'!$B:$B,"Runway ML",'כל ההוצאות'!$F:$F,"נובמבר 2026") | AJ25: =SUMIFS('כל ההוצאות'!$D:$D,'כל ההוצאות'!$B:$B,"Runway ML",'כל ההוצאות'!$F:$F,"דצמבר 2026") | AK25: =SUMIFS('כל ההוצאות'!$E:$E,'כל ההוצאות'!$B:$B,"Runway ML",'כל ההוצאות'!$F:$F,"דצמבר 2026") | AL25: =SUM(B25,D25,F25,H25,J25,L25,N25,P25,R25,T25,V25,X25,Z25,AB25,AD25,AF25,AH25,AJ25) | AM25: =SUM(C25,E25,G25,I25,K25,M25,O25,Q25,S25,U25,W25,Y25,AA25,AC25,AE25,AG25,AI25,AK25)
A26: Supabase | B26: =SUMIFS('כל ההוצאות'!$D:$D,'כל ההוצאות'!$B:$B,"Supabase",'כל ההוצאות'!$F:$F,"יולי 2025") | C26: =SUMIFS('כל ההוצאות'!$E:$E,'כל ההוצאות'!$B:$B,"Supabase",'כל ההוצאות'!$F:$F,"יולי 2025") | D26: =SUMIFS('כל ההוצאות'!$D:$D,'כל ההוצאות'!$B:$B,"Supabase",'כל ההוצאות'!$F:$F,"אוגוסט 2025") | E26: =SUMIFS('כל ההוצאות'!$E:$E,'כל ההוצאות'!$B:$B,"Supabase",'כל ההוצאות'!$F:$F,"אוגוסט 2025") | F26: =SUMIFS('כל ההוצאות'!$D:$D,'כל ההוצאות'!$B:$B,"Supabase",'כל ההוצאות'!$F:$F,"ספטמבר 2025") | G26: =SUMIFS('כל ההוצאות'!$E:$E,'כל ההוצאות'!$B:$B,"Supabase",'כל ההוצאות'!$F:$F,"ספטמבר 2025") | H26: =SUMIFS('כל ההוצאות'!$D:$D,'כל ההוצאות'!$B:$B,"Supabase",'כל ההוצאות'!$F:$F,"אוקטובר 2025") | I26: =SUMIFS('כל ההוצאות'!$E:$E,'כל ההוצאות'!$B:$B,"Supabase",'כל ההוצאות'!$F:$F,"אוקטובר 2025") | J26: =SUMIFS('כל ההוצאות'!$D:$D,'כל ההוצאות'!$B:$B,"Supabase",'כל ההוצאות'!$F:$F,"נובמבר 2025") | K26: =SUMIFS('כל ההוצאות'!$E:$E,'כל ההוצאות'!$B:$B,"Supabase",'כל ההוצאות'!$F:$F,"נובמבר 2025") | L26: =SUMIFS('כל ההוצאות'!$D:$D,'כל ההוצאות'!$B:$B,"Supabase",'כל ההוצאות'!$F:$F,"דצמבר 2025") | M26: =SUMIFS('כל ההוצאות'!$E:$E,'כל ההוצאות'!$B:$B,"Supabase",'כל ההוצאות'!$F:$F,"דצמבר 2025") | N26: =SUMIFS('כל ההוצאות'!$D:$D,'כל ההוצאות'!$B:$B,"Supabase",'כל ההוצאות'!$F:$F,"ינואר 2026") | O26: =SUMIFS('כל ההוצאות'!$E:$E,'כל ההוצאות'!$B:$B,"Supabase",'כל ההוצאות'!$F:$F,"ינואר 2026") | P26: =SUMIFS('כל ההוצאות'!$D:$D,'כל ההוצאות'!$B:$B,"Supabase",'כל ההוצאות'!$F:$F,"פברואר 2026") | Q26: =SUMIFS('כל ההוצאות'!$E:$E,'כל ההוצאות'!$B:$B,"Supabase",'כל ההוצאות'!$F:$F,"פברואר 2026") | R26: =SUMIFS('כל ההוצאות'!$D:$D,'כל ההוצאות'!$B:$B,"Supabase",'כל ההוצאות'!$F:$F,"מרץ 2026") | S26: =SUMIFS('כל ההוצאות'!$E:$E,'כל ההוצאות'!$B:$B,"Supabase",'כל ההוצאות'!$F:$F,"מרץ 2026") | T26: =SUMIFS('כל ההוצאות'!$D:$D,'כל ההוצאות'!$B:$B,"Supabase",'כל ההוצאות'!$F:$F,"אפריל 2026") | U26: =SUMIFS('כל ההוצאות'!$E:$E,'כל ההוצאות'!$B:$B,"Supabase",'כל ההוצאות'!$F:$F,"אפריל 2026") | V26: =SUMIFS('כל ההוצאות'!$D:$D,'כל ההוצאות'!$B:$B,"Supabase",'כל ההוצאות'!$F:$F,"מאי 2026") | W26: =SUMIFS('כל ההוצאות'!$E:$E,'כל ההוצאות'!$B:$B,"Supabase",'כל ההוצאות'!$F:$F,"מאי 2026") | X26: =SUMIFS('כל ההוצאות'!$D:$D,'כל ההוצאות'!$B:$B,"Supabase",'כל ההוצאות'!$F:$F,"יוני 2026") | Y26: =SUMIFS('כל ההוצאות'!$E:$E,'כל ההוצאות'!$B:$B,"Supabase",'כל ההוצאות'!$F:$F,"יוני 2026") | Z26: =SUMIFS('כל ההוצאות'!$D:$D,'כל ההוצאות'!$B:$B,"Supabase",'כל ההוצאות'!$F:$F,"יולי 2026") | AA26: =SUMIFS('כל ההוצאות'!$E:$E,'כל ההוצאות'!$B:$B,"Supabase",'כל ההוצאות'!$F:$F,"יולי 2026") | AB26: =SUMIFS('כל ההוצאות'!$D:$D,'כל ההוצאות'!$B:$B,"Supabase",'כל ההוצאות'!$F:$F,"אוגוסט 2026") | AC26: =SUMIFS('כל ההוצאות'!$E:$E,'כל ההוצאות'!$B:$B,"Supabase",'כל ההוצאות'!$F:$F,"אוגוסט 2026") | AD26: =SUMIFS('כל ההוצאות'!$D:$D,'כל ההוצאות'!$B:$B,"Supabase",'כל ההוצאות'!$F:$F,"ספטמבר 2026") | AE26: =SUMIFS('כל ההוצאות'!$E:$E,'כל ההוצאות'!$B:$B,"Supabase",'כל ההוצאות'!$F:$F,"ספטמבר 2026") | AF26: =SUMIFS('כל ההוצאות'!$D:$D,'כל ההוצאות'!$B:$B,"Supabase",'כל ההוצאות'!$F:$F,"אוקטובר 2026") | AG26: =SUMIFS('כל ההוצאות'!$E:$E,'כל ההוצאות'!$B:$B,"Supabase",'כל ההוצאות'!$F:$F,"אוקטובר 2026") | AH26: =SUMIFS('כל ההוצאות'!$D:$D,'כל ההוצאות'!$B:$B,"Supabase",'כל ההוצאות'!$F:$F,"נובמבר 2026") | AI26: =SUMIFS('כל ההוצאות'!$E:$E,'כל ההוצאות'!$B:$B,"Supabase",'כל ההוצאות'!$F:$F,"נובמבר 2026") | AJ26: =SUMIFS('כל ההוצאות'!$D:$D,'כל ההוצאות'!$B:$B,"Supabase",'כל ההוצאות'!$F:$F,"דצמבר 2026") | AK26: =SUMIFS('כל ההוצאות'!$E:$E,'כל ההוצאות'!$B:$B,"Supabase",'כל ההוצאות'!$F:$F,"דצמבר 2026") | AL26: =SUM(B26,D26,F26,H26,J26,L26,N26,P26,R26,T26,V26,X26,Z26,AB26,AD26,AF26,AH26,AJ26) | AM26: =SUM(C26,E26,G26,I26,K26,M26,O26,Q26,S26,U26,W26,Y26,AA26,AC26,AE26,AG26,AI26,AK26)
A27: Timeless | B27: =SUMIFS('כל ההוצאות'!$D:$D,'כל ההוצאות'!$B:$B,"Timeless",'כל ההוצאות'!$F:$F,"יולי 2025") | C27: =SUMIFS('כל ההוצאות'!$E:$E,'כל ההוצאות'!$B:$B,"Timeless",'כל ההוצאות'!$F:$F,"יולי 2025") | D27: =SUMIFS('כל ההוצאות'!$D:$D,'כל ההוצאות'!$B:$B,"Timeless",'כל ההוצאות'!$F:$F,"אוגוסט 2025") | E27: =SUMIFS('כל ההוצאות'!$E:$E,'כל ההוצאות'!$B:$B,"Timeless",'כל ההוצאות'!$F:$F,"אוגוסט 2025") | F27: =SUMIFS('כל ההוצאות'!$D:$D,'כל ההוצאות'!$B:$B,"Timeless",'כל ההוצאות'!$F:$F,"ספטמבר 2025") | G27: =SUMIFS('כל ההוצאות'!$E:$E,'כל ההוצאות'!$B:$B,"Timeless",'כל ההוצאות'!$F:$F,"ספטמבר 2025") | H27: =SUMIFS('כל ההוצאות'!$D:$D,'כל ההוצאות'!$B:$B,"Timeless",'כל ההוצאות'!$F:$F,"אוקטובר 2025") | I27: =SUMIFS('כל ההוצאות'!$E:$E,'כל ההוצאות'!$B:$B,"Timeless",'כל ההוצאות'!$F:$F,"אוקטובר 2025") | J27: =SUMIFS('כל ההוצאות'!$D:$D,'כל ההוצאות'!$B:$B,"Timeless",'כל ההוצאות'!$F:$F,"נובמבר 2025") | K27: =SUMIFS('כל ההוצאות'!$E:$E,'כל ההוצאות'!$B:$B,"Timeless",'כל ההוצאות'!$F:$F,"נובמבר 2025") | L27: =SUMIFS('כל ההוצאות'!$D:$D,'כל ההוצאות'!$B:$B,"Timeless",'כל ההוצאות'!$F:$F,"דצמבר 2025") | M27: =SUMIFS('כל ההוצאות'!$E:$E,'כל ההוצאות'!$B:$B,"Timeless",'כל ההוצאות'!$F:$F,"דצמבר 2025") | N27: =SUMIFS('כל ההוצאות'!$D:$D,'כל ההוצאות'!$B:$B,"Timeless",'כל ההוצאות'!$F:$F,"ינואר 2026") | O27: =SUMIFS('כל ההוצאות'!$E:$E,'כל ההוצאות'!$B:$B,"Timeless",'כל ההוצאות'!$F:$F,"ינואר 2026") | P27: =SUMIFS('כל ההוצאות'!$D:$D,'כל ההוצאות'!$B:$B,"Timeless",'כל ההוצאות'!$F:$F,"פברואר 2026") | Q27: =SUMIFS('כל ההוצאות'!$E:$E,'כל ההוצאות'!$B:$B,"Timeless",'כל ההוצאות'!$F:$F,"פברואר 2026") | R27: =SUMIFS('כל ההוצאות'!$D:$D,'כל ההוצאות'!$B:$B,"Timeless",'כל ההוצאות'!$F:$F,"מרץ 2026") | S27: =SUMIFS('כל ההוצאות'!$E:$E,'כל ההוצאות'!$B:$B,"Timeless",'כל ההוצאות'!$F:$F,"מרץ 2026") | T27: =SUMIFS('כל ההוצאות'!$D:$D,'כל ההוצאות'!$B:$B,"Timeless",'כל ההוצאות'!$F:$F,"אפריל 2026") | U27: =SUMIFS('כל ההוצאות'!$E:$E,'כל ההוצאות'!$B:$B,"Timeless",'כל ההוצאות'!$F:$F,"אפריל 2026") | V27: =SUMIFS('כל ההוצאות'!$D:$D,'כל ההוצאות'!$B:$B,"Timeless",'כל ההוצאות'!$F:$F,"מאי 2026") | W27: =SUMIFS('כל ההוצאות'!$E:$E,'כל ההוצאות'!$B:$B,"Timeless",'כל ההוצאות'!$F:$F,"מאי 2026") | X27: =SUMIFS('כל ההוצאות'!$D:$D,'כל ההוצאות'!$B:$B,"Timeless",'כל ההוצאות'!$F:$F,"יוני 2026") | Y27: =SUMIFS('כל ההוצאות'!$E:$E,'כל ההוצאות'!$B:$B,"Timeless",'כל ההוצאות'!$F:$F,"יוני 2026") | Z27: =SUMIFS('כל ההוצאות'!$D:$D,'כל ההוצאות'!$B:$B,"Timeless",'כל ההוצאות'!$F:$F,"יולי 2026") | AA27: =SUMIFS('כל ההוצאות'!$E:$E,'כל ההוצאות'!$B:$B,"Timeless",'כל ההוצאות'!$F:$F,"יולי 2026") | AB27: =SUMIFS('כל ההוצאות'!$D:$D,'כל ההוצאות'!$B:$B,"Timeless",'כל ההוצאות'!$F:$F,"אוגוסט 2026") | AC27: =SUMIFS('כל ההוצאות'!$E:$E,'כל ההוצאות'!$B:$B,"Timeless",'כל ההוצאות'!$F:$F,"אוגוסט 2026") | AD27: =SUMIFS('כל ההוצאות'!$D:$D,'כל ההוצאות'!$B:$B,"Timeless",'כל ההוצאות'!$F:$F,"ספטמבר 2026") | AE27: =SUMIFS('כל ההוצאות'!$E:$E,'כל ההוצאות'!$B:$B,"Timeless",'כל ההוצאות'!$F:$F,"ספטמבר 2026") | AF27: =SUMIFS('כל ההוצאות'!$D:$D,'כל ההוצאות'!$B:$B,"Timeless",'כל ההוצאות'!$F:$F,"אוקטובר 2026") | AG27: =SUMIFS('כל ההוצאות'!$E:$E,'כל ההוצאות'!$B:$B,"Timeless",'כל ההוצאות'!$F:$F,"אוקטובר 2026") | AH27: =SUMIFS('כל ההוצאות'!$D:$D,'כל ההוצאות'!$B:$B,"Timeless",'כל ההוצאות'!$F:$F,"נובמבר 2026") | AI27: =SUMIFS('כל ההוצאות'!$E:$E,'כל ההוצאות'!$B:$B,"Timeless",'כל ההוצאות'!$F:$F,"נובמבר 2026") | AJ27: =SUMIFS('כל ההוצאות'!$D:$D,'כל ההוצאות'!$B:$B,"Timeless",'כל ההוצאות'!$F:$F,"דצמבר 2026") | AK27: =SUMIFS('כל ההוצאות'!$E:$E,'כל ההוצאות'!$B:$B,"Timeless",'כל ההוצאות'!$F:$F,"דצמבר 2026") | AL27: =SUM(B27,D27,F27,H27,J27,L27,N27,P27,R27,T27,V27,X27,Z27,AB27,AD27,AF27,AH27,AJ27) | AM27: =SUM(C27,E27,G27,I27,K27,M27,O27,Q27,S27,U27,W27,Y27,AA27,AC27,AE27,AG27,AI27,AK27)
A28: סה"כ חודשי | B28: =SUM(B5:B27) | C28: =SUM(C5:C27) | D28: =SUM(D5:D27) | E28: =SUM(E5:E27) | F28: =SUM(F5:F27) | G28: =SUM(G5:G27) | H28: =SUM(H5:H27) | I28: =SUM(I5:I27) | ... AM28: =SUM(AM5:AM27)

Sheet דוח שנתי
A1: דוח שנתי – AI & Business Tools Expenses
A2: סיכום הוצאות לפי חודש – יולי 2025 – דצמבר 2026
A3: חודש | B3: תאריך | C3: הוצאה ($) | D3: הוצאה (₪) | E3: % מסה"כ | F3: הערות
A4: יולי 2025 | B4: July 2025 | C4: =SUMIF('כל ההוצאות'!$F:$F,"יולי 2025",'כל ההוצאות'!$D:$D) | D4: =SUMIF('כל ההוצאות'!$F:$F,"יולי 2025",'כל ההוצאות'!$E:$E) | E4: =IF(C23>0,C4/C23,0)
A5: אוגוסט 2025 | B5: August 2025 | C5: =SUMIF('כל ההוצאות'!$F:$F,"אוגוסט 2025",'כל ההוצאות'!$D:$D) | D5: =SUMIF('כל ההוצאות'!$F:$F,"אוגוסט 2025",'כל ההוצאות'!$E:$E) | E5: =IF(C23>0,C5/C23,0)
A6: ספטמבר 2025 | B6: September 2025 | C6: =SUMIF('כל ההוצאות'!$F:$F,"ספטמבר 2025",'כל ההוצאות'!$D:$D) | D6: =SUMIF('כל ההוצאות'!$F:$F,"ספטמבר 2025",'כל ההוצאות'!$E:$E) | E6: =IF(C23>0,C6/C23,0)
A7: אוקטובר 2025 | B7: October 2025 | C7: =SUMIF('כל ההוצאות'!$F:$F,"אוקטובר 2025",'כל ההוצאות'!$D:$D) | D7: =SUMIF('כל ההוצאות'!$F:$F,"אוקטובר 2025",'כל ההוצאות'!$E:$E) | E7: =IF(C23>0,C7/C23,0)
A8: נובמבר 2025 | B8: November 2025 | C8: =SUMIF('כל ההוצאות'!$F:$F,"נובמבר 2025",'כל ההוצאות'!$D:$D) | D8: =SUMIF('כל ההוצאות'!$F:$F,"נובמבר 2025",'כל ההוצאות'!$E:$E) | E8: =IF(C23>0,C8/C23,0)
A9: דצמבר 2025 | B9: December 2025 | C9: =SUMIF('כל ההוצאות'!$F:$F,"דצמבר 2025",'כל ההוצאות'!$D:$D) | D9: =SUMIF('כל ההוצאות'!$F:$F,"דצמבר 2025",'כל ההוצאות'!$E:$E) | E9: =IF(C23>0,C9/C23,0)
A10: ינואר 2026 | B10: January 2026 | C10: =SUMIF('כל ההוצאות'!$F:$F,"ינואר 2026",'כל ההוצאות'!$D:$D) | D10: =SUMIF('כל ההוצאות'!$F:$F,"ינואר 2026",'כל ההוצאות'!$E:$E) | E10: =IF(C23>0,C10/C23,0)
A11: פברואר 2026 | B11: February 2026 | C11: =SUMIF('כל ההוצאות'!$F:$F,"פברואר 2026",'כל ההוצאות'!$D:$D) | D11: =SUMIF('כל ההוצאות'!$F:$F,"פברואר 2026",'כל ההוצאות'!$E:$E) | E11: =IF(C23>0,C11/C23,0)
A12: מרץ 2026 | B12: March 2026 | C12: =SUMIF('כל ההוצאות'!$F:$F,"מרץ 2026",'כל ההוצאות'!$D:$D) | D12: =SUMIF('כל ההוצאות'!$F:$F,"מרץ 2026",'כל ההוצאות'!$E:$E) | E12: =IF(C23>0,C12/C23,0)
A13: אפריל 2026 | B13: April 2026 | C13: =SUMIF('כל ההוצאות'!$F:$F,"אפריל 2026",'כל ההוצאות'!$D:$D) | D13: =SUMIF('כל ההוצאות'!$F:$F,"אפריל 2026",'כל ההוצאות'!$E:$E) | E13: =IF(C23>0,C13/C23,0)
A14: מאי 2026 | B14: May 2026 | C14: =SUMIF('כל ההוצאות'!$F:$F,"מאי 2026",'כל ההוצאות'!$D:$D) | D14: =SUMIF('כל ההוצאות'!$F:$F,"מאי 2026",'כל ההוצאות'!$E:$E) | E14: =IF(C23>0,C14/C23,0)
A15: יוני 2026 | B15: June 2026 | C15: =SUMIF('כל ההוצאות'!$F:$F,"יוני 2026",'כל ההוצאות'!$D:$D) | D15: =SUMIF('כל ההוצאות'!$F:$F,"יוני 2026",'כל ההוצאות'!$E:$E) | E15: =IF(C23>0,C15/C23,0)
A16: יולי 2026 | B16: July 2026 | C16: =SUMIF('כל ההוצאות'!$F:$F,"יולי 2026",'כל ההוצאות'!$D:$D) | D16: =SUMIF('כל ההוצאות'!$F:$F,"יולי 2026",'כל ההוצאות'!$E:$E) | E16: =IF(C23>0,C16/C23,0)
A17: אוגוסט 2026 | B17: August 2026 | C17: =SUMIF('כל ההוצאות'!$F:$F,"אוגוסט 2026",'כל ההוצאות'!$D:$D) | D17: =SUMIF('כל ההוצאות'!$F:$F,"אוגוסט 2026",'כל ההוצאות'!$E:$E) | E17: =IF(C23>0,C17/C23,0)
A18: ספטמבר 2026 | B18: September 2026 | C18: =SUMIF('כל ההוצאות'!$F:$F,"ספטמבר 2026",'כל ההוצאות'!$D:$D) | D18: =SUMIF('כל ההוצאות'!$F:$F,"ספטמבר 2026",'כל ההוצאות'!$E:$E) | E18: =IF(C23>0,C18/C23,0)
A19: אוקטובר 2026 | B19: October 2026 | C19: =SUMIF('כל ההוצאות'!$F:$F,"אוקטובר 2026",'כל ההוצאות'!$D:$D) | D19: =SUMIF('כל ההוצאות'!$F:$F,"אוקטובר 2026",'כל ההוצאות'!$E:$E) | E19: =IF(C23>0,C19/C23,0)
A20: נובמבר 2026 | B20: November 2026 | C20: =SUMIF('כל ההוצאות'!$F:$F,"נובמבר 2026",'כל ההוצאות'!$D:$D) | D20: =SUMIF('כל ההוצאות'!$F:$F,"נובמבר 2026",'כל ההוצאות'!$E:$E) | E20: =IF(C23>0,C20/C23,0)
A21: דצמבר 2026 | B21: December 2026 | C21: =SUMIF('כל ההוצאות'!$F:$F,"דצמבר 2026",'כל ההוצאות'!$D:$D) | D21: =SUMIF('כל ההוצאות'!$F:$F,"דצמבר 2026",'כל ההוצאות'!$E:$E) | E21: =IF(C23>0,C21/C23,0)
A23: סה"כ שנתי | C23: =SUM(C4:C21) | D23: =SUM(D4:D21) | E23: 100%
A24: ממוצע חודשי | C24: =AVERAGE(C4:C21) | D24: =AVERAGE(D4:D21)
